{
  "clip_path": "C:\\Users\\scott\\OneDrive\\SoccerVideoMedia\\out\\atomic_clips\\_quarantine\\010__CROSS__t1541.10-t1547.90.__CINEMATIC.__CINEMATIC.__CINEMATIC.__CINEMATIC.__CINEMATIC.__CINEMATIC.__CINEMATIC.__CINEMATIC.mp4",
  "source_sha1_64": "30e4bfac41918374",
  "meta": {
    "duration_s": 9.875,
    "width": 1080,
    "height": 1920,
    "fps": "24/1"
  },
  "steps": {},
  "errors": [],
  "master_path": "C:/Users/scott/soccer-video/out/games/2025-11-05__TSC_vs_TSC_Navy/MASTER.mp4",
  "master_rel": "out/games/2025-11-05__TSC_vs_TSC_Navy/MASTER.mp4",
  "t_start_s": 1541.1,
  "t_end_s": 1547.9
}