{
  "clip_path": "C:\\Users\\scott\\OneDrive\\SoccerVideoMedia\\out\\atomic_clips\\2025-09-20__TSC_vs_RVFC\\031__2025-09-20__TSC_vs_RVFC__PRESSURE_SHOT__t1964.00-t1975.00_portrait_POST.__CINEMATIC.__CINEMATIC.__CINEMATIC.__CINEMATIC.__CINEMATIC.__CINEMATIC.__CINEMATIC.mp4",
  "source_sha1_64": "07e686bd0f04e97c",
  "meta": {
    "duration_s": 11.0,
    "width": 1080,
    "height": 1920,
    "fps": "24/1"
  },
  "steps": {
    "portrait_render": {
      "done": false,
      "preset": "cinematic",
      "error": "render failed"
    }
  },
  "errors": [
    {
      "step": "portrait_render",
      "message": "render failed",
      "at": "2026-02-12T00:04:58+00:00"
    }
  ],
  "master_path": "C:/Users/scott/soccer-video/out/games/2025-09-20__TSC_vs_RVFC/MASTER.mp4",
  "master_rel": "out/games/2025-09-20__TSC_vs_RVFC/MASTER.mp4",
  "t_start_s": 1964.0,
  "t_end_s": 1975.0
}