[
    {
        "clip_id":  "4|2025-09-13|TSC|NEOFC|GOAL|266.50|283.10",
        "index":  4,
        "date":  "2025-09-13",
        "homeTeam":  "TSC",
        "awayTeam":  "NEOFC",
        "label":  "GOAL",
        "tStart":  266.5,
        "tEnd":  283.1,
        "duration_sec":  16.6,
        "orientation":  "portrait",
        "hasDebug":  true,
        "hasFinal":  true,
        "root_dir":  "C:\\Users\\scott\\soccer-video\\out\\autoframe_work\\cinematic\\004__2025-09-13__TSC_vs_NEOFC__GOAL__t266.50-t283.10.__DEBUG_FINAL_portrait_FINAL",
        "proxy_path":  "C:\\Users\\scott\\soccer-video\\out\\autoframe_work\\cinematic\\004__2025-09-13__TSC_vs_NEOFC__GOAL__t266.50-t283.10.__DEBUG_FINAL_portrait_FINAL\\proxy.mp4",
        "trf_path":  "C:\\Users\\scott\\soccer-video\\out\\autoframe_work\\cinematic\\004__2025-09-13__TSC_vs_NEOFC__GOAL__t266.50-t283.10.__DEBUG_FINAL_portrait_FINAL\\follow\\transforms.trf",
        "stabilized_path":  "C:\\Users\\scott\\soccer-video\\out\\autoframe_work\\cinematic\\004__2025-09-13__TSC_vs_NEOFC__GOAL__t266.50-t283.10.__DEBUG_FINAL_portrait_FINAL\\follow\\stabilized.mp4",
        "branded_matches":  "C:\\Users\\scott\\soccer-video\\out\\portrait_reels\\branded\\001__2025-09-13__TSC_vs_NEOFC__SHOT__t155.50-t166.40_portrait_BRAND.mp4;C:\\Users\\scott\\soccer-video\\out\\portrait_reels\\branded\\001__2025-09-13__TSC_vs_NEOFC__SHOT__t155.50-t166.40_portrait_POST.mp4;C:\\Users\\scott\\soccer-video\\out\\portrait_reels\\branded\\002__2025-09-13__TSC_vs_NEOFC__GOAL__t180.80-t191.20_portrait_POST.mp4;C:\\Users\\scott\\soccer-video\\out\\portrait_reels\\branded\\003__2025-09-13__TSC_vs_NEOFC__BUILD_UP__t224.80-t248.70_portrait_POST.mp4;C:\\Users\\scott\\soccer-video\\out\\portrait_reels\\branded\\004__2025-09-13__TSC_vs_NEOFC__GOAL__t266.50-t283.10_portrait_POST.mp4;C:\\Users\\scott\\soccer-video\\out\\portrait_reels\\branded\\005__2025-09-13__TSC_vs_NEOFC__CORNER__t417.90-t431.60_portrait_POST.mp4;C:\\Users\\scott\\soccer-video\\out\\portrait_reels\\branded\\006__2025-09-13__TSC_vs_NEOFC__DEFENSE__t699.30-t711.50_portrait_POST.mp4;C:\\Users\\scott\\soccer-video\\out\\portrait_reels\\branded\\007__2025-09-13__TSC_vs_NEOFC__DRIBBLING__t982.00-t987.90_portrait_POST.mp4;C:\\Users\\scott\\soccer-video\\out\\portrait_reels\\branded\\008__2025-09-13__TSC_vs_NEOFC__SHOT__t1247.80-t1259.20_portrait_POST.mp4;C:\\Users\\scott\\soccer-video\\out\\portrait_reels\\branded\\009__2025-09-13__TSC_vs_NEOFC__SHOT__t1420.40-t1438.20_portrait_POST.mp4;C:\\Users\\scott\\soccer-video\\out\\portrait_reels\\branded\\010__2025-09-13__TSC_vs_NEOFC__CROSS__t1541.10-t1547.90_portrait_POST.mp4;C:\\Users\\scott\\soccer-video\\out\\portrait_reels\\branded\\011__2025-09-13__TSC_vs_NEOFC__SHOTS__t1655.00-t1670.30_portrait_POST.mp4;C:\\Users\\scott\\soccer-video\\out\\portrait_reels\\branded\\012__2025-09-13__TSC_vs_NEOFC__GOAL__t1705.20-t1708.50_portrait_POST.mp4;C:\\Users\\scott\\soccer-video\\out\\portrait_reels\\branded\\013__2025-09-13__TSC_vs_NEOFC__GOAL__t1767.50-t1772.60_portrait_POST.mp4;C:\\Users\\scott\\soccer-video\\out\\portrait_reels\\branded\\014__2025-09-13__TSC_vs_NEOFC__GOAL__t1904.20-t1925.20_portrait_POST.mp4;C:\\Users\\scott\\soccer-video\\out\\portrait_reels\\branded\\015__2025-09-13__TSC_vs_NEOFC__DRIBBLING__t1972.50-t1980.70_portrait_POST.mp4;C:\\Users\\scott\\soccer-video\\out\\portrait_reels\\branded\\016__2025-09-13__TSC_vs_NEOFC__SHOT__t2029.90-t2039.50_portrait_POST.mp4;C:\\Users\\scott\\soccer-video\\out\\portrait_reels\\branded\\017__2025-09-13__TSC_vs_NEOFC__SHOT__t2284.90-t2298.20_portrait_POST.mp4;C:\\Users\\scott\\soccer-video\\out\\portrait_reels\\branded\\018__2025-09-13__TSC_vs_NEOFC__SHOT__t2419.50-t2425.60_portrait_POST.mp4;C:\\Users\\scott\\soccer-video\\out\\portrait_reels\\branded\\019__2025-09-13__TSC_vs_NEOFC__SHOT__t2633.00-t2638.10_portrait_POST.mp4;C:\\Users\\scott\\soccer-video\\out\\portrait_reels\\branded\\020__2025-09-13__TSC_vs_NEOFC__GOAL__t2816.60-t2831.80_portrait_POST.mp4;C:\\Users\\scott\\soccer-video\\out\\portrait_reels\\branded\\021__2025-09-13__TSC_vs_NEOFC__SHOT__t2860.70-t2873.00_portrait_POST.mp4;C:\\Users\\scott\\soccer-video\\out\\portrait_reels\\branded\\023__2025-09-13__TSC_vs_NEOFC__SHOT__t3098.90-t3108.80_portrait_POST.mp4",
        "proxy_exists":  "true",
        "trf_exists":  "true",
        "stabilized_exists":  "true",
        "has_branded":  "true",
        "notes":  "seen in legacy index"
    },
    {
        "clip_id":  "2|2025-09-13|TSC|NEOFC|GOAL|180.80|191.20",
        "index":  2,
        "date":  "2025-09-13",
        "homeTeam":  "TSC",
        "awayTeam":  "NEOFC",
        "label":  "GOAL",
        "tStart":  180.8,
        "tEnd":  191.2,
        "duration_sec":  10.4,
        "orientation":  "portrait",
        "hasDebug":  true,
        "hasFinal":  true,
        "root_dir":  "C:\\Users\\scott\\soccer-video\\out\\autoframe_work\\cinematic\\002__2025-09-13__TSC_vs_NEOFC__GOAL__t180.80-t191.20.__DEBUG_FINAL_portrait_FINAL",
        "proxy_path":  "C:\\Users\\scott\\soccer-video\\out\\autoframe_work\\cinematic\\002__2025-09-13__TSC_vs_NEOFC__GOAL__t180.80-t191.20.__DEBUG_FINAL_portrait_FINAL\\proxy.mp4",
        "trf_path":  "C:\\Users\\scott\\soccer-video\\out\\autoframe_work\\cinematic\\002__2025-09-13__TSC_vs_NEOFC__GOAL__t180.80-t191.20.__DEBUG_FINAL_portrait_FINAL\\follow\\transforms.trf",
        "stabilized_path":  "C:\\Users\\scott\\soccer-video\\out\\autoframe_work\\cinematic\\002__2025-09-13__TSC_vs_NEOFC__GOAL__t180.80-t191.20.__DEBUG_FINAL_portrait_FINAL\\follow\\stabilized.mp4",
        "branded_matches":  "C:\\Users\\scott\\soccer-video\\out\\portrait_reels\\branded\\001__2025-09-13__TSC_vs_NEOFC__SHOT__t155.50-t166.40_portrait_BRAND.mp4;C:\\Users\\scott\\soccer-video\\out\\portrait_reels\\branded\\001__2025-09-13__TSC_vs_NEOFC__SHOT__t155.50-t166.40_portrait_POST.mp4;C:\\Users\\scott\\soccer-video\\out\\portrait_reels\\branded\\002__2025-09-13__TSC_vs_NEOFC__GOAL__t180.80-t191.20_portrait_POST.mp4;C:\\Users\\scott\\soccer-video\\out\\portrait_reels\\branded\\003__2025-09-13__TSC_vs_NEOFC__BUILD_UP__t224.80-t248.70_portrait_POST.mp4;C:\\Users\\scott\\soccer-video\\out\\portrait_reels\\branded\\004__2025-09-13__TSC_vs_NEOFC__GOAL__t266.50-t283.10_portrait_POST.mp4;C:\\Users\\scott\\soccer-video\\out\\portrait_reels\\branded\\005__2025-09-13__TSC_vs_NEOFC__CORNER__t417.90-t431.60_portrait_POST.mp4;C:\\Users\\scott\\soccer-video\\out\\portrait_reels\\branded\\006__2025-09-13__TSC_vs_NEOFC__DEFENSE__t699.30-t711.50_portrait_POST.mp4;C:\\Users\\scott\\soccer-video\\out\\portrait_reels\\branded\\007__2025-09-13__TSC_vs_NEOFC__DRIBBLING__t982.00-t987.90_portrait_POST.mp4;C:\\Users\\scott\\soccer-video\\out\\portrait_reels\\branded\\008__2025-09-13__TSC_vs_NEOFC__SHOT__t1247.80-t1259.20_portrait_POST.mp4;C:\\Users\\scott\\soccer-video\\out\\portrait_reels\\branded\\009__2025-09-13__TSC_vs_NEOFC__SHOT__t1420.40-t1438.20_portrait_POST.mp4;C:\\Users\\scott\\soccer-video\\out\\portrait_reels\\branded\\010__2025-09-13__TSC_vs_NEOFC__CROSS__t1541.10-t1547.90_portrait_POST.mp4;C:\\Users\\scott\\soccer-video\\out\\portrait_reels\\branded\\011__2025-09-13__TSC_vs_NEOFC__SHOTS__t1655.00-t1670.30_portrait_POST.mp4;C:\\Users\\scott\\soccer-video\\out\\portrait_reels\\branded\\012__2025-09-13__TSC_vs_NEOFC__GOAL__t1705.20-t1708.50_portrait_POST.mp4;C:\\Users\\scott\\soccer-video\\out\\portrait_reels\\branded\\013__2025-09-13__TSC_vs_NEOFC__GOAL__t1767.50-t1772.60_portrait_POST.mp4;C:\\Users\\scott\\soccer-video\\out\\portrait_reels\\branded\\014__2025-09-13__TSC_vs_NEOFC__GOAL__t1904.20-t1925.20_portrait_POST.mp4;C:\\Users\\scott\\soccer-video\\out\\portrait_reels\\branded\\015__2025-09-13__TSC_vs_NEOFC__DRIBBLING__t1972.50-t1980.70_portrait_POST.mp4;C:\\Users\\scott\\soccer-video\\out\\portrait_reels\\branded\\016__2025-09-13__TSC_vs_NEOFC__SHOT__t2029.90-t2039.50_portrait_POST.mp4;C:\\Users\\scott\\soccer-video\\out\\portrait_reels\\branded\\017__2025-09-13__TSC_vs_NEOFC__SHOT__t2284.90-t2298.20_portrait_POST.mp4;C:\\Users\\scott\\soccer-video\\out\\portrait_reels\\branded\\018__2025-09-13__TSC_vs_NEOFC__SHOT__t2419.50-t2425.60_portrait_POST.mp4;C:\\Users\\scott\\soccer-video\\out\\portrait_reels\\branded\\019__2025-09-13__TSC_vs_NEOFC__SHOT__t2633.00-t2638.10_portrait_POST.mp4;C:\\Users\\scott\\soccer-video\\out\\portrait_reels\\branded\\020__2025-09-13__TSC_vs_NEOFC__GOAL__t2816.60-t2831.80_portrait_POST.mp4;C:\\Users\\scott\\soccer-video\\out\\portrait_reels\\branded\\021__2025-09-13__TSC_vs_NEOFC__SHOT__t2860.70-t2873.00_portrait_POST.mp4;C:\\Users\\scott\\soccer-video\\out\\portrait_reels\\branded\\023__2025-09-13__TSC_vs_NEOFC__SHOT__t3098.90-t3108.80_portrait_POST.mp4",
        "proxy_exists":  "true",
        "trf_exists":  "true",
        "stabilized_exists":  "true",
        "has_branded":  "true",
        "notes":  "seen in legacy index"
    },
    {
        "clip_id":  "15|2025-10-04|TSC|FC_Tulsa_Black|BUILD_UP_SHOT|1705.00|1721.00",
        "index":  15,
        "date":  "2025-10-04",
        "homeTeam":  "TSC",
        "awayTeam":  "FC_Tulsa_Black",
        "label":  "BUILD_UP_SHOT",
        "tStart":  1705,
        "tEnd":  1721,
        "duration_sec":  16,
        "orientation":  "unknown",
        "hasDebug":  false,
        "hasFinal":  false,
        "root_dir":  "C:\\Users\\scott\\soccer-video\\out\\autoframe_work\\cinematic\\015__2025-10-04__TSC_vs_FC_Tulsa_Black__BUILD_UP_SHOT__t1705.00-t1721.00",
        "proxy_path":  "C:\\Users\\scott\\soccer-video\\out\\autoframe_work\\cinematic\\015__2025-10-04__TSC_vs_FC_Tulsa_Black__BUILD_UP_SHOT__t1705.00-t1721.00\\proxy.mp4",
        "trf_path":  "C:\\Users\\scott\\soccer-video\\out\\autoframe_work\\cinematic\\015__2025-10-04__TSC_vs_FC_Tulsa_Black__BUILD_UP_SHOT__t1705.00-t1721.00\\follow\\transforms.trf",
        "stabilized_path":  "C:\\Users\\scott\\soccer-video\\out\\autoframe_work\\cinematic\\015__2025-10-04__TSC_vs_FC_Tulsa_Black__BUILD_UP_SHOT__t1705.00-t1721.00\\follow\\stabilized.mp4",
        "branded_matches":  "C:\\Users\\scott\\soccer-video\\out\\portrait_reels\\branded\\001__2025-10-04__TSC_vs_FC_Tulsa_Black__DRIBBLING__t387.00-t412.00_portrait_BRAND.mp4;C:\\Users\\scott\\soccer-video\\out\\portrait_reels\\branded\\001__2025-10-04__TSC_vs_FC_Tulsa_Black__DRIBBLING__t387.00-t412.00_portrait_POST.mp4;C:\\Users\\scott\\soccer-video\\out\\portrait_reels\\branded\\002__2025-10-04__TSC_vs_FC_Tulsa_Black__BUILD_UP__t421.00-t449.00_portrait_POST.mp4;C:\\Users\\scott\\soccer-video\\out\\portrait_reels\\branded\\003__2025-10-04__TSC_vs_FC_Tulsa_Black__BUILD_UP__t458.00-t487.00_portrait_POST.mp4;C:\\Users\\scott\\soccer-video\\out\\portrait_reels\\branded\\004__2025-10-04__TSC_vs_FC_Tulsa_Black__BUILD_UP__t495.00-t513.00_portrait_POST.mp4;C:\\Users\\scott\\soccer-video\\out\\portrait_reels\\branded\\005__2025-10-04__TSC_vs_FC_Tulsa_Black__SHOT__t600.00-t607.00_portrait_POST.mp4;C:\\Users\\scott\\soccer-video\\out\\portrait_reels\\branded\\006__2025-10-04__TSC_vs_FC_Tulsa_Black__BUILD_UP_GOAL__t674.00-t717.00_portrait_POST.mp4;C:\\Users\\scott\\soccer-video\\out\\portrait_reels\\branded\\007__2025-10-04__TSC_vs_FC_Tulsa_Black__BUILD_UP_SHOT__t767.00-t785.00_portrait_POST.mp4;C:\\Users\\scott\\soccer-video\\out\\portrait_reels\\branded\\008__2025-10-04__TSC_vs_FC_Tulsa_Black__BUILD_UP_SHOT__t1025.00-t1040.00_portrait_POST.mp4;C:\\Users\\scott\\soccer-video\\out\\portrait_reels\\branded\\009__2025-10-04__TSC_vs_FC_Tulsa_Black__PRESSURE_SHOT__t1046.00-t1057.00_portrait_POST.mp4;C:\\Users\\scott\\soccer-video\\out\\portrait_reels\\branded\\010__2025-10-04__TSC_vs_FC_Tulsa_Black__BUILD_UP_SHOT__t1058.00-t1080.00_portrait_POST.mp4;C:\\Users\\scott\\soccer-video\\out\\portrait_reels\\branded\\011__2025-10-04__TSC_vs_FC_Tulsa_Black__BUILD_UP_SHOT__t1198.00-t1222.00_portrait_POST.mp4;C:\\Users\\scott\\soccer-video\\out\\portrait_reels\\branded\\012__2025-10-04__TSC_vs_FC_Tulsa_Black__PRESSURE_GOAL__t1239.00-t1253.00_portrait_POST.mp4;C:\\Users\\scott\\soccer-video\\out\\portrait_reels\\branded\\013__2025-10-04__TSC_vs_FC_Tulsa_Black__BUILD_UP_PLAY__t1290.00-t1306.00_portrait_POST.mp4;C:\\Users\\scott\\soccer-video\\out\\portrait_reels\\branded\\014__2025-10-04__TSC_vs_FC_Tulsa_Black__SHOT__t1626.00-t1637.00_portrait_POST.mp4;C:\\Users\\scott\\soccer-video\\out\\portrait_reels\\branded\\015__2025-10-04__TSC_vs_FC_Tulsa_Black__BUILD_UP_SHOT__t1705.00-t1721.00_portrait_POST.mp4",
        "proxy_exists":  "true",
        "trf_exists":  "true",
        "stabilized_exists":  "true",
        "has_branded":  "true",
        "notes":  "seen in legacy index"
    },
    {
        "clip_id":  "3|2025-09-13|TSC|NEOFC|BUILD_UP|224.80|248.70",
        "index":  3,
        "date":  "2025-09-13",
        "homeTeam":  "TSC",
        "awayTeam":  "NEOFC",
        "label":  "BUILD_UP",
        "tStart":  224.8,
        "tEnd":  248.7,
        "duration_sec":  23.9,
        "orientation":  "portrait",
        "hasDebug":  true,
        "hasFinal":  true,
        "root_dir":  "C:\\Users\\scott\\soccer-video\\out\\autoframe_work\\cinematic\\003__2025-09-13__TSC_vs_NEOFC__BUILD_UP__t224.80-t248.70.__DEBUG_FINAL_portrait_FINAL",
        "proxy_path":  "C:\\Users\\scott\\soccer-video\\out\\autoframe_work\\cinematic\\003__2025-09-13__TSC_vs_NEOFC__BUILD_UP__t224.80-t248.70.__DEBUG_FINAL_portrait_FINAL\\proxy.mp4",
        "trf_path":  "C:\\Users\\scott\\soccer-video\\out\\autoframe_work\\cinematic\\003__2025-09-13__TSC_vs_NEOFC__BUILD_UP__t224.80-t248.70.__DEBUG_FINAL_portrait_FINAL\\follow\\transforms.trf",
        "stabilized_path":  "C:\\Users\\scott\\soccer-video\\out\\autoframe_work\\cinematic\\003__2025-09-13__TSC_vs_NEOFC__BUILD_UP__t224.80-t248.70.__DEBUG_FINAL_portrait_FINAL\\follow\\stabilized.mp4",
        "branded_matches":  "C:\\Users\\scott\\soccer-video\\out\\portrait_reels\\branded\\001__2025-09-13__TSC_vs_NEOFC__SHOT__t155.50-t166.40_portrait_BRAND.mp4;C:\\Users\\scott\\soccer-video\\out\\portrait_reels\\branded\\001__2025-09-13__TSC_vs_NEOFC__SHOT__t155.50-t166.40_portrait_POST.mp4;C:\\Users\\scott\\soccer-video\\out\\portrait_reels\\branded\\002__2025-09-13__TSC_vs_NEOFC__GOAL__t180.80-t191.20_portrait_POST.mp4;C:\\Users\\scott\\soccer-video\\out\\portrait_reels\\branded\\003__2025-09-13__TSC_vs_NEOFC__BUILD_UP__t224.80-t248.70_portrait_POST.mp4;C:\\Users\\scott\\soccer-video\\out\\portrait_reels\\branded\\004__2025-09-13__TSC_vs_NEOFC__GOAL__t266.50-t283.10_portrait_POST.mp4;C:\\Users\\scott\\soccer-video\\out\\portrait_reels\\branded\\005__2025-09-13__TSC_vs_NEOFC__CORNER__t417.90-t431.60_portrait_POST.mp4;C:\\Users\\scott\\soccer-video\\out\\portrait_reels\\branded\\006__2025-09-13__TSC_vs_NEOFC__DEFENSE__t699.30-t711.50_portrait_POST.mp4;C:\\Users\\scott\\soccer-video\\out\\portrait_reels\\branded\\007__2025-09-13__TSC_vs_NEOFC__DRIBBLING__t982.00-t987.90_portrait_POST.mp4;C:\\Users\\scott\\soccer-video\\out\\portrait_reels\\branded\\008__2025-09-13__TSC_vs_NEOFC__SHOT__t1247.80-t1259.20_portrait_POST.mp4;C:\\Users\\scott\\soccer-video\\out\\portrait_reels\\branded\\009__2025-09-13__TSC_vs_NEOFC__SHOT__t1420.40-t1438.20_portrait_POST.mp4;C:\\Users\\scott\\soccer-video\\out\\portrait_reels\\branded\\010__2025-09-13__TSC_vs_NEOFC__CROSS__t1541.10-t1547.90_portrait_POST.mp4;C:\\Users\\scott\\soccer-video\\out\\portrait_reels\\branded\\011__2025-09-13__TSC_vs_NEOFC__SHOTS__t1655.00-t1670.30_portrait_POST.mp4;C:\\Users\\scott\\soccer-video\\out\\portrait_reels\\branded\\012__2025-09-13__TSC_vs_NEOFC__GOAL__t1705.20-t1708.50_portrait_POST.mp4;C:\\Users\\scott\\soccer-video\\out\\portrait_reels\\branded\\013__2025-09-13__TSC_vs_NEOFC__GOAL__t1767.50-t1772.60_portrait_POST.mp4;C:\\Users\\scott\\soccer-video\\out\\portrait_reels\\branded\\014__2025-09-13__TSC_vs_NEOFC__GOAL__t1904.20-t1925.20_portrait_POST.mp4;C:\\Users\\scott\\soccer-video\\out\\portrait_reels\\branded\\015__2025-09-13__TSC_vs_NEOFC__DRIBBLING__t1972.50-t1980.70_portrait_POST.mp4;C:\\Users\\scott\\soccer-video\\out\\portrait_reels\\branded\\016__2025-09-13__TSC_vs_NEOFC__SHOT__t2029.90-t2039.50_portrait_POST.mp4;C:\\Users\\scott\\soccer-video\\out\\portrait_reels\\branded\\017__2025-09-13__TSC_vs_NEOFC__SHOT__t2284.90-t2298.20_portrait_POST.mp4;C:\\Users\\scott\\soccer-video\\out\\portrait_reels\\branded\\018__2025-09-13__TSC_vs_NEOFC__SHOT__t2419.50-t2425.60_portrait_POST.mp4;C:\\Users\\scott\\soccer-video\\out\\portrait_reels\\branded\\019__2025-09-13__TSC_vs_NEOFC__SHOT__t2633.00-t2638.10_portrait_POST.mp4;C:\\Users\\scott\\soccer-video\\out\\portrait_reels\\branded\\020__2025-09-13__TSC_vs_NEOFC__GOAL__t2816.60-t2831.80_portrait_POST.mp4;C:\\Users\\scott\\soccer-video\\out\\portrait_reels\\branded\\021__2025-09-13__TSC_vs_NEOFC__SHOT__t2860.70-t2873.00_portrait_POST.mp4;C:\\Users\\scott\\soccer-video\\out\\portrait_reels\\branded\\023__2025-09-13__TSC_vs_NEOFC__SHOT__t3098.90-t3108.80_portrait_POST.mp4",
        "proxy_exists":  "true",
        "trf_exists":  "true",
        "stabilized_exists":  "true",
        "has_branded":  "true",
        "notes":  "seen in legacy index"
    },
    {
        "clip_id":  "6|2025-09-13|TSC|NEOFC|DEFENSE|699.30|711.50",
        "index":  6,
        "date":  "2025-09-13",
        "homeTeam":  "TSC",
        "awayTeam":  "NEOFC",
        "label":  "DEFENSE",
        "tStart":  699.3,
        "tEnd":  711.5,
        "duration_sec":  12.2,
        "orientation":  "portrait",
        "hasDebug":  true,
        "hasFinal":  true,
        "root_dir":  "C:\\Users\\scott\\soccer-video\\out\\autoframe_work\\cinematic\\006__2025-09-13__TSC_vs_NEOFC__DEFENSE__t699.30-t711.50.__DEBUG_FINAL_portrait_FINAL",
        "proxy_path":  "C:\\Users\\scott\\soccer-video\\out\\autoframe_work\\cinematic\\006__2025-09-13__TSC_vs_NEOFC__DEFENSE__t699.30-t711.50.__DEBUG_FINAL_portrait_FINAL\\proxy.mp4",
        "trf_path":  "C:\\Users\\scott\\soccer-video\\out\\autoframe_work\\cinematic\\006__2025-09-13__TSC_vs_NEOFC__DEFENSE__t699.30-t711.50.__DEBUG_FINAL_portrait_FINAL\\follow\\transforms.trf",
        "stabilized_path":  "C:\\Users\\scott\\soccer-video\\out\\autoframe_work\\cinematic\\006__2025-09-13__TSC_vs_NEOFC__DEFENSE__t699.30-t711.50.__DEBUG_FINAL_portrait_FINAL\\follow\\stabilized.mp4",
        "branded_matches":  "C:\\Users\\scott\\soccer-video\\out\\portrait_reels\\branded\\001__2025-09-13__TSC_vs_NEOFC__SHOT__t155.50-t166.40_portrait_BRAND.mp4;C:\\Users\\scott\\soccer-video\\out\\portrait_reels\\branded\\001__2025-09-13__TSC_vs_NEOFC__SHOT__t155.50-t166.40_portrait_POST.mp4;C:\\Users\\scott\\soccer-video\\out\\portrait_reels\\branded\\002__2025-09-13__TSC_vs_NEOFC__GOAL__t180.80-t191.20_portrait_POST.mp4;C:\\Users\\scott\\soccer-video\\out\\portrait_reels\\branded\\003__2025-09-13__TSC_vs_NEOFC__BUILD_UP__t224.80-t248.70_portrait_POST.mp4;C:\\Users\\scott\\soccer-video\\out\\portrait_reels\\branded\\004__2025-09-13__TSC_vs_NEOFC__GOAL__t266.50-t283.10_portrait_POST.mp4;C:\\Users\\scott\\soccer-video\\out\\portrait_reels\\branded\\005__2025-09-13__TSC_vs_NEOFC__CORNER__t417.90-t431.60_portrait_POST.mp4;C:\\Users\\scott\\soccer-video\\out\\portrait_reels\\branded\\006__2025-09-13__TSC_vs_NEOFC__DEFENSE__t699.30-t711.50_portrait_POST.mp4;C:\\Users\\scott\\soccer-video\\out\\portrait_reels\\branded\\007__2025-09-13__TSC_vs_NEOFC__DRIBBLING__t982.00-t987.90_portrait_POST.mp4;C:\\Users\\scott\\soccer-video\\out\\portrait_reels\\branded\\008__2025-09-13__TSC_vs_NEOFC__SHOT__t1247.80-t1259.20_portrait_POST.mp4;C:\\Users\\scott\\soccer-video\\out\\portrait_reels\\branded\\009__2025-09-13__TSC_vs_NEOFC__SHOT__t1420.40-t1438.20_portrait_POST.mp4;C:\\Users\\scott\\soccer-video\\out\\portrait_reels\\branded\\010__2025-09-13__TSC_vs_NEOFC__CROSS__t1541.10-t1547.90_portrait_POST.mp4;C:\\Users\\scott\\soccer-video\\out\\portrait_reels\\branded\\011__2025-09-13__TSC_vs_NEOFC__SHOTS__t1655.00-t1670.30_portrait_POST.mp4;C:\\Users\\scott\\soccer-video\\out\\portrait_reels\\branded\\012__2025-09-13__TSC_vs_NEOFC__GOAL__t1705.20-t1708.50_portrait_POST.mp4;C:\\Users\\scott\\soccer-video\\out\\portrait_reels\\branded\\013__2025-09-13__TSC_vs_NEOFC__GOAL__t1767.50-t1772.60_portrait_POST.mp4;C:\\Users\\scott\\soccer-video\\out\\portrait_reels\\branded\\014__2025-09-13__TSC_vs_NEOFC__GOAL__t1904.20-t1925.20_portrait_POST.mp4;C:\\Users\\scott\\soccer-video\\out\\portrait_reels\\branded\\015__2025-09-13__TSC_vs_NEOFC__DRIBBLING__t1972.50-t1980.70_portrait_POST.mp4;C:\\Users\\scott\\soccer-video\\out\\portrait_reels\\branded\\016__2025-09-13__TSC_vs_NEOFC__SHOT__t2029.90-t2039.50_portrait_POST.mp4;C:\\Users\\scott\\soccer-video\\out\\portrait_reels\\branded\\017__2025-09-13__TSC_vs_NEOFC__SHOT__t2284.90-t2298.20_portrait_POST.mp4;C:\\Users\\scott\\soccer-video\\out\\portrait_reels\\branded\\018__2025-09-13__TSC_vs_NEOFC__SHOT__t2419.50-t2425.60_portrait_POST.mp4;C:\\Users\\scott\\soccer-video\\out\\portrait_reels\\branded\\019__2025-09-13__TSC_vs_NEOFC__SHOT__t2633.00-t2638.10_portrait_POST.mp4;C:\\Users\\scott\\soccer-video\\out\\portrait_reels\\branded\\020__2025-09-13__TSC_vs_NEOFC__GOAL__t2816.60-t2831.80_portrait_POST.mp4;C:\\Users\\scott\\soccer-video\\out\\portrait_reels\\branded\\021__2025-09-13__TSC_vs_NEOFC__SHOT__t2860.70-t2873.00_portrait_POST.mp4;C:\\Users\\scott\\soccer-video\\out\\portrait_reels\\branded\\023__2025-09-13__TSC_vs_NEOFC__SHOT__t3098.90-t3108.80_portrait_POST.mp4",
        "proxy_exists":  "true",
        "trf_exists":  "true",
        "stabilized_exists":  "true",
        "has_branded":  "true",
        "notes":  "seen in legacy index"
    },
    {
        "clip_id":  "7|2025-10-04|TSC|FC_Tulsa_Black|BUILD_UP_SHOT|767.00|785",
        "index":  7,
        "date":  "2025-10-04",
        "homeTeam":  "TSC",
        "awayTeam":  "FC_Tulsa_Black",
        "label":  "BUILD_UP_SHOT",
        "tStart":  767,
        "tEnd":  785,
        "duration_sec":  18,
        "orientation":  "portrait",
        "hasDebug":  false,
        "hasFinal":  true,
        "root_dir":  "C:\\Users\\scott\\soccer-video\\out\\autoframe_work\\cinematic\\007__2025-10-04__TSC_vs_FC_Tulsa_Black__BUILD_UP_SHOT__t767.00-t785.00_portrait_FINAL",
        "proxy_path":  "C:\\Users\\scott\\soccer-video\\out\\autoframe_work\\cinematic\\007__2025-10-04__TSC_vs_FC_Tulsa_Black__BUILD_UP_SHOT__t767.00-t785.00_portrait_FINAL\\proxy.mp4",
        "trf_path":  "C:\\Users\\scott\\soccer-video\\out\\autoframe_work\\cinematic\\007__2025-10-04__TSC_vs_FC_Tulsa_Black__BUILD_UP_SHOT__t767.00-t785.00_portrait_FINAL\\follow\\transforms.trf",
        "stabilized_path":  "C:\\Users\\scott\\soccer-video\\out\\autoframe_work\\cinematic\\007__2025-10-04__TSC_vs_FC_Tulsa_Black__BUILD_UP_SHOT__t767.00-t785.00_portrait_FINAL\\follow\\stabilized.mp4",
        "branded_matches":  "C:\\Users\\scott\\soccer-video\\out\\portrait_reels\\branded\\001__2025-10-04__TSC_vs_FC_Tulsa_Black__DRIBBLING__t387.00-t412.00_portrait_BRAND.mp4;C:\\Users\\scott\\soccer-video\\out\\portrait_reels\\branded\\001__2025-10-04__TSC_vs_FC_Tulsa_Black__DRIBBLING__t387.00-t412.00_portrait_POST.mp4;C:\\Users\\scott\\soccer-video\\out\\portrait_reels\\branded\\002__2025-10-04__TSC_vs_FC_Tulsa_Black__BUILD_UP__t421.00-t449.00_portrait_POST.mp4;C:\\Users\\scott\\soccer-video\\out\\portrait_reels\\branded\\003__2025-10-04__TSC_vs_FC_Tulsa_Black__BUILD_UP__t458.00-t487.00_portrait_POST.mp4;C:\\Users\\scott\\soccer-video\\out\\portrait_reels\\branded\\004__2025-10-04__TSC_vs_FC_Tulsa_Black__BUILD_UP__t495.00-t513.00_portrait_POST.mp4;C:\\Users\\scott\\soccer-video\\out\\portrait_reels\\branded\\005__2025-10-04__TSC_vs_FC_Tulsa_Black__SHOT__t600.00-t607.00_portrait_POST.mp4;C:\\Users\\scott\\soccer-video\\out\\portrait_reels\\branded\\006__2025-10-04__TSC_vs_FC_Tulsa_Black__BUILD_UP_GOAL__t674.00-t717.00_portrait_POST.mp4;C:\\Users\\scott\\soccer-video\\out\\portrait_reels\\branded\\007__2025-10-04__TSC_vs_FC_Tulsa_Black__BUILD_UP_SHOT__t767.00-t785.00_portrait_POST.mp4;C:\\Users\\scott\\soccer-video\\out\\portrait_reels\\branded\\008__2025-10-04__TSC_vs_FC_Tulsa_Black__BUILD_UP_SHOT__t1025.00-t1040.00_portrait_POST.mp4;C:\\Users\\scott\\soccer-video\\out\\portrait_reels\\branded\\009__2025-10-04__TSC_vs_FC_Tulsa_Black__PRESSURE_SHOT__t1046.00-t1057.00_portrait_POST.mp4;C:\\Users\\scott\\soccer-video\\out\\portrait_reels\\branded\\010__2025-10-04__TSC_vs_FC_Tulsa_Black__BUILD_UP_SHOT__t1058.00-t1080.00_portrait_POST.mp4;C:\\Users\\scott\\soccer-video\\out\\portrait_reels\\branded\\011__2025-10-04__TSC_vs_FC_Tulsa_Black__BUILD_UP_SHOT__t1198.00-t1222.00_portrait_POST.mp4;C:\\Users\\scott\\soccer-video\\out\\portrait_reels\\branded\\012__2025-10-04__TSC_vs_FC_Tulsa_Black__PRESSURE_GOAL__t1239.00-t1253.00_portrait_POST.mp4;C:\\Users\\scott\\soccer-video\\out\\portrait_reels\\branded\\013__2025-10-04__TSC_vs_FC_Tulsa_Black__BUILD_UP_PLAY__t1290.00-t1306.00_portrait_POST.mp4;C:\\Users\\scott\\soccer-video\\out\\portrait_reels\\branded\\014__2025-10-04__TSC_vs_FC_Tulsa_Black__SHOT__t1626.00-t1637.00_portrait_POST.mp4;C:\\Users\\scott\\soccer-video\\out\\portrait_reels\\branded\\015__2025-10-04__TSC_vs_FC_Tulsa_Black__BUILD_UP_SHOT__t1705.00-t1721.00_portrait_POST.mp4",
        "proxy_exists":  "true",
        "trf_exists":  "true",
        "stabilized_exists":  "true",
        "has_branded":  "true",
        "notes":  "seen in legacy index"
    },
    {
        "clip_id":  "6|2025-10-04|TSC|FC_Tulsa_Black|BUILD_UP_GOAL|674.00|717",
        "index":  6,
        "date":  "2025-10-04",
        "homeTeam":  "TSC",
        "awayTeam":  "FC_Tulsa_Black",
        "label":  "BUILD_UP_GOAL",
        "tStart":  674,
        "tEnd":  717,
        "duration_sec":  43,
        "orientation":  "portrait",
        "hasDebug":  false,
        "hasFinal":  true,
        "root_dir":  "C:\\Users\\scott\\soccer-video\\out\\autoframe_work\\cinematic\\006__2025-10-04__TSC_vs_FC_Tulsa_Black__BUILD_UP_GOAL__t674.00-t717.00_portrait_FINAL",
        "proxy_path":  "C:\\Users\\scott\\soccer-video\\out\\autoframe_work\\cinematic\\006__2025-10-04__TSC_vs_FC_Tulsa_Black__BUILD_UP_GOAL__t674.00-t717.00_portrait_FINAL\\proxy.mp4",
        "trf_path":  "C:\\Users\\scott\\soccer-video\\out\\autoframe_work\\cinematic\\006__2025-10-04__TSC_vs_FC_Tulsa_Black__BUILD_UP_GOAL__t674.00-t717.00_portrait_FINAL\\follow\\transforms.trf",
        "stabilized_path":  "C:\\Users\\scott\\soccer-video\\out\\autoframe_work\\cinematic\\006__2025-10-04__TSC_vs_FC_Tulsa_Black__BUILD_UP_GOAL__t674.00-t717.00_portrait_FINAL\\follow\\stabilized.mp4",
        "branded_matches":  "C:\\Users\\scott\\soccer-video\\out\\portrait_reels\\branded\\001__2025-10-04__TSC_vs_FC_Tulsa_Black__DRIBBLING__t387.00-t412.00_portrait_BRAND.mp4;C:\\Users\\scott\\soccer-video\\out\\portrait_reels\\branded\\001__2025-10-04__TSC_vs_FC_Tulsa_Black__DRIBBLING__t387.00-t412.00_portrait_POST.mp4;C:\\Users\\scott\\soccer-video\\out\\portrait_reels\\branded\\002__2025-10-04__TSC_vs_FC_Tulsa_Black__BUILD_UP__t421.00-t449.00_portrait_POST.mp4;C:\\Users\\scott\\soccer-video\\out\\portrait_reels\\branded\\003__2025-10-04__TSC_vs_FC_Tulsa_Black__BUILD_UP__t458.00-t487.00_portrait_POST.mp4;C:\\Users\\scott\\soccer-video\\out\\portrait_reels\\branded\\004__2025-10-04__TSC_vs_FC_Tulsa_Black__BUILD_UP__t495.00-t513.00_portrait_POST.mp4;C:\\Users\\scott\\soccer-video\\out\\portrait_reels\\branded\\005__2025-10-04__TSC_vs_FC_Tulsa_Black__SHOT__t600.00-t607.00_portrait_POST.mp4;C:\\Users\\scott\\soccer-video\\out\\portrait_reels\\branded\\006__2025-10-04__TSC_vs_FC_Tulsa_Black__BUILD_UP_GOAL__t674.00-t717.00_portrait_POST.mp4;C:\\Users\\scott\\soccer-video\\out\\portrait_reels\\branded\\007__2025-10-04__TSC_vs_FC_Tulsa_Black__BUILD_UP_SHOT__t767.00-t785.00_portrait_POST.mp4;C:\\Users\\scott\\soccer-video\\out\\portrait_reels\\branded\\008__2025-10-04__TSC_vs_FC_Tulsa_Black__BUILD_UP_SHOT__t1025.00-t1040.00_portrait_POST.mp4;C:\\Users\\scott\\soccer-video\\out\\portrait_reels\\branded\\009__2025-10-04__TSC_vs_FC_Tulsa_Black__PRESSURE_SHOT__t1046.00-t1057.00_portrait_POST.mp4;C:\\Users\\scott\\soccer-video\\out\\portrait_reels\\branded\\010__2025-10-04__TSC_vs_FC_Tulsa_Black__BUILD_UP_SHOT__t1058.00-t1080.00_portrait_POST.mp4;C:\\Users\\scott\\soccer-video\\out\\portrait_reels\\branded\\011__2025-10-04__TSC_vs_FC_Tulsa_Black__BUILD_UP_SHOT__t1198.00-t1222.00_portrait_POST.mp4;C:\\Users\\scott\\soccer-video\\out\\portrait_reels\\branded\\012__2025-10-04__TSC_vs_FC_Tulsa_Black__PRESSURE_GOAL__t1239.00-t1253.00_portrait_POST.mp4;C:\\Users\\scott\\soccer-video\\out\\portrait_reels\\branded\\013__2025-10-04__TSC_vs_FC_Tulsa_Black__BUILD_UP_PLAY__t1290.00-t1306.00_portrait_POST.mp4;C:\\Users\\scott\\soccer-video\\out\\portrait_reels\\branded\\014__2025-10-04__TSC_vs_FC_Tulsa_Black__SHOT__t1626.00-t1637.00_portrait_POST.mp4;C:\\Users\\scott\\soccer-video\\out\\portrait_reels\\branded\\015__2025-10-04__TSC_vs_FC_Tulsa_Black__BUILD_UP_SHOT__t1705.00-t1721.00_portrait_POST.mp4",
        "proxy_exists":  "true",
        "trf_exists":  "true",
        "stabilized_exists":  "true",
        "has_branded":  "true",
        "notes":  "seen in legacy index"
    },
    {
        "clip_id":  "22||||SHOT|3028.10|3059.70",
        "index":  22,
        "date":  null,
        "homeTeam":  null,
        "awayTeam":  null,
        "label":  "SHOT",
        "tStart":  3028.1,
        "tEnd":  3059.7,
        "duration_sec":  31.6,
        "orientation":  "portrait",
        "hasDebug":  true,
        "hasFinal":  true,
        "root_dir":  "C:\\Users\\scott\\soccer-video\\out\\autoframe_work\\cinematic\\022__SHOT__t3028.10-t3059.70.__DEBUG_FINAL_portrait_FINAL",
        "proxy_path":  "C:\\Users\\scott\\soccer-video\\out\\autoframe_work\\cinematic\\022__SHOT__t3028.10-t3059.70.__DEBUG_FINAL_portrait_FINAL\\proxy.mp4",
        "trf_path":  "C:\\Users\\scott\\soccer-video\\out\\autoframe_work\\cinematic\\022__SHOT__t3028.10-t3059.70.__DEBUG_FINAL_portrait_FINAL\\follow\\transforms.trf",
        "stabilized_path":  "C:\\Users\\scott\\soccer-video\\out\\autoframe_work\\cinematic\\022__SHOT__t3028.10-t3059.70.__DEBUG_FINAL_portrait_FINAL\\follow\\stabilized.mp4",
        "branded_matches":  "",
        "proxy_exists":  "true",
        "trf_exists":  "true",
        "stabilized_exists":  "true",
        "has_branded":  "false",
        "notes":  "seen in legacy index"
    },
    {
        "clip_id":  "11|2025-10-04|TSC|FC_Tulsa_Black|BUILD_UP_SHOT|1198.00|1222",
        "index":  11,
        "date":  "2025-10-04",
        "homeTeam":  "TSC",
        "awayTeam":  "FC_Tulsa_Black",
        "label":  "BUILD_UP_SHOT",
        "tStart":  1198,
        "tEnd":  1222,
        "duration_sec":  24,
        "orientation":  "portrait",
        "hasDebug":  false,
        "hasFinal":  true,
        "root_dir":  "C:\\Users\\scott\\soccer-video\\out\\autoframe_work\\cinematic\\011__2025-10-04__TSC_vs_FC_Tulsa_Black__BUILD_UP_SHOT__t1198.00-t1222.00_portrait_FINAL",
        "proxy_path":  "C:\\Users\\scott\\soccer-video\\out\\autoframe_work\\cinematic\\011__2025-10-04__TSC_vs_FC_Tulsa_Black__BUILD_UP_SHOT__t1198.00-t1222.00_portrait_FINAL\\proxy.mp4",
        "trf_path":  "C:\\Users\\scott\\soccer-video\\out\\autoframe_work\\cinematic\\011__2025-10-04__TSC_vs_FC_Tulsa_Black__BUILD_UP_SHOT__t1198.00-t1222.00_portrait_FINAL\\follow\\transforms.trf",
        "stabilized_path":  "C:\\Users\\scott\\soccer-video\\out\\autoframe_work\\cinematic\\011__2025-10-04__TSC_vs_FC_Tulsa_Black__BUILD_UP_SHOT__t1198.00-t1222.00_portrait_FINAL\\follow\\stabilized.mp4",
        "branded_matches":  "C:\\Users\\scott\\soccer-video\\out\\portrait_reels\\branded\\001__2025-10-04__TSC_vs_FC_Tulsa_Black__DRIBBLING__t387.00-t412.00_portrait_BRAND.mp4;C:\\Users\\scott\\soccer-video\\out\\portrait_reels\\branded\\001__2025-10-04__TSC_vs_FC_Tulsa_Black__DRIBBLING__t387.00-t412.00_portrait_POST.mp4;C:\\Users\\scott\\soccer-video\\out\\portrait_reels\\branded\\002__2025-10-04__TSC_vs_FC_Tulsa_Black__BUILD_UP__t421.00-t449.00_portrait_POST.mp4;C:\\Users\\scott\\soccer-video\\out\\portrait_reels\\branded\\003__2025-10-04__TSC_vs_FC_Tulsa_Black__BUILD_UP__t458.00-t487.00_portrait_POST.mp4;C:\\Users\\scott\\soccer-video\\out\\portrait_reels\\branded\\004__2025-10-04__TSC_vs_FC_Tulsa_Black__BUILD_UP__t495.00-t513.00_portrait_POST.mp4;C:\\Users\\scott\\soccer-video\\out\\portrait_reels\\branded\\005__2025-10-04__TSC_vs_FC_Tulsa_Black__SHOT__t600.00-t607.00_portrait_POST.mp4;C:\\Users\\scott\\soccer-video\\out\\portrait_reels\\branded\\006__2025-10-04__TSC_vs_FC_Tulsa_Black__BUILD_UP_GOAL__t674.00-t717.00_portrait_POST.mp4;C:\\Users\\scott\\soccer-video\\out\\portrait_reels\\branded\\007__2025-10-04__TSC_vs_FC_Tulsa_Black__BUILD_UP_SHOT__t767.00-t785.00_portrait_POST.mp4;C:\\Users\\scott\\soccer-video\\out\\portrait_reels\\branded\\008__2025-10-04__TSC_vs_FC_Tulsa_Black__BUILD_UP_SHOT__t1025.00-t1040.00_portrait_POST.mp4;C:\\Users\\scott\\soccer-video\\out\\portrait_reels\\branded\\009__2025-10-04__TSC_vs_FC_Tulsa_Black__PRESSURE_SHOT__t1046.00-t1057.00_portrait_POST.mp4;C:\\Users\\scott\\soccer-video\\out\\portrait_reels\\branded\\010__2025-10-04__TSC_vs_FC_Tulsa_Black__BUILD_UP_SHOT__t1058.00-t1080.00_portrait_POST.mp4;C:\\Users\\scott\\soccer-video\\out\\portrait_reels\\branded\\011__2025-10-04__TSC_vs_FC_Tulsa_Black__BUILD_UP_SHOT__t1198.00-t1222.00_portrait_POST.mp4;C:\\Users\\scott\\soccer-video\\out\\portrait_reels\\branded\\012__2025-10-04__TSC_vs_FC_Tulsa_Black__PRESSURE_GOAL__t1239.00-t1253.00_portrait_POST.mp4;C:\\Users\\scott\\soccer-video\\out\\portrait_reels\\branded\\013__2025-10-04__TSC_vs_FC_Tulsa_Black__BUILD_UP_PLAY__t1290.00-t1306.00_portrait_POST.mp4;C:\\Users\\scott\\soccer-video\\out\\portrait_reels\\branded\\014__2025-10-04__TSC_vs_FC_Tulsa_Black__SHOT__t1626.00-t1637.00_portrait_POST.mp4;C:\\Users\\scott\\soccer-video\\out\\portrait_reels\\branded\\015__2025-10-04__TSC_vs_FC_Tulsa_Black__BUILD_UP_SHOT__t1705.00-t1721.00_portrait_POST.mp4",
        "proxy_exists":  "true",
        "trf_exists":  "true",
        "stabilized_exists":  "true",
        "has_branded":  "true",
        "notes":  "seen in legacy index"
    },
    {
        "clip_id":  "1|2025-10-04|TSC|FC_Tulsa_Black|DRIBBLING|387.00|412",
        "index":  1,
        "date":  "2025-10-04",
        "homeTeam":  "TSC",
        "awayTeam":  "FC_Tulsa_Black",
        "label":  "DRIBBLING",
        "tStart":  387,
        "tEnd":  412,
        "duration_sec":  25,
        "orientation":  "portrait",
        "hasDebug":  false,
        "hasFinal":  true,
        "root_dir":  "C:\\Users\\scott\\soccer-video\\out\\autoframe_work\\cinematic\\001__2025-10-04__TSC_vs_FC_Tulsa_Black__DRIBBLING__t387.00-t412.00_portrait_FINAL",
        "proxy_path":  "C:\\Users\\scott\\soccer-video\\out\\autoframe_work\\cinematic\\001__2025-10-04__TSC_vs_FC_Tulsa_Black__DRIBBLING__t387.00-t412.00_portrait_FINAL\\proxy.mp4",
        "trf_path":  "C:\\Users\\scott\\soccer-video\\out\\autoframe_work\\cinematic\\001__2025-10-04__TSC_vs_FC_Tulsa_Black__DRIBBLING__t387.00-t412.00_portrait_FINAL\\follow\\transforms.trf",
        "stabilized_path":  "C:\\Users\\scott\\soccer-video\\out\\autoframe_work\\cinematic\\001__2025-10-04__TSC_vs_FC_Tulsa_Black__DRIBBLING__t387.00-t412.00_portrait_FINAL\\follow\\stabilized.mp4",
        "branded_matches":  "C:\\Users\\scott\\soccer-video\\out\\portrait_reels\\branded\\001__2025-10-04__TSC_vs_FC_Tulsa_Black__DRIBBLING__t387.00-t412.00_portrait_BRAND.mp4;C:\\Users\\scott\\soccer-video\\out\\portrait_reels\\branded\\001__2025-10-04__TSC_vs_FC_Tulsa_Black__DRIBBLING__t387.00-t412.00_portrait_POST.mp4;C:\\Users\\scott\\soccer-video\\out\\portrait_reels\\branded\\002__2025-10-04__TSC_vs_FC_Tulsa_Black__BUILD_UP__t421.00-t449.00_portrait_POST.mp4;C:\\Users\\scott\\soccer-video\\out\\portrait_reels\\branded\\003__2025-10-04__TSC_vs_FC_Tulsa_Black__BUILD_UP__t458.00-t487.00_portrait_POST.mp4;C:\\Users\\scott\\soccer-video\\out\\portrait_reels\\branded\\004__2025-10-04__TSC_vs_FC_Tulsa_Black__BUILD_UP__t495.00-t513.00_portrait_POST.mp4;C:\\Users\\scott\\soccer-video\\out\\portrait_reels\\branded\\005__2025-10-04__TSC_vs_FC_Tulsa_Black__SHOT__t600.00-t607.00_portrait_POST.mp4;C:\\Users\\scott\\soccer-video\\out\\portrait_reels\\branded\\006__2025-10-04__TSC_vs_FC_Tulsa_Black__BUILD_UP_GOAL__t674.00-t717.00_portrait_POST.mp4;C:\\Users\\scott\\soccer-video\\out\\portrait_reels\\branded\\007__2025-10-04__TSC_vs_FC_Tulsa_Black__BUILD_UP_SHOT__t767.00-t785.00_portrait_POST.mp4;C:\\Users\\scott\\soccer-video\\out\\portrait_reels\\branded\\008__2025-10-04__TSC_vs_FC_Tulsa_Black__BUILD_UP_SHOT__t1025.00-t1040.00_portrait_POST.mp4;C:\\Users\\scott\\soccer-video\\out\\portrait_reels\\branded\\009__2025-10-04__TSC_vs_FC_Tulsa_Black__PRESSURE_SHOT__t1046.00-t1057.00_portrait_POST.mp4;C:\\Users\\scott\\soccer-video\\out\\portrait_reels\\branded\\010__2025-10-04__TSC_vs_FC_Tulsa_Black__BUILD_UP_SHOT__t1058.00-t1080.00_portrait_POST.mp4;C:\\Users\\scott\\soccer-video\\out\\portrait_reels\\branded\\011__2025-10-04__TSC_vs_FC_Tulsa_Black__BUILD_UP_SHOT__t1198.00-t1222.00_portrait_POST.mp4;C:\\Users\\scott\\soccer-video\\out\\portrait_reels\\branded\\012__2025-10-04__TSC_vs_FC_Tulsa_Black__PRESSURE_GOAL__t1239.00-t1253.00_portrait_POST.mp4;C:\\Users\\scott\\soccer-video\\out\\portrait_reels\\branded\\013__2025-10-04__TSC_vs_FC_Tulsa_Black__BUILD_UP_PLAY__t1290.00-t1306.00_portrait_POST.mp4;C:\\Users\\scott\\soccer-video\\out\\portrait_reels\\branded\\014__2025-10-04__TSC_vs_FC_Tulsa_Black__SHOT__t1626.00-t1637.00_portrait_POST.mp4;C:\\Users\\scott\\soccer-video\\out\\portrait_reels\\branded\\015__2025-10-04__TSC_vs_FC_Tulsa_Black__BUILD_UP_SHOT__t1705.00-t1721.00_portrait_POST.mp4",
        "proxy_exists":  "true",
        "trf_exists":  "true",
        "stabilized_exists":  "true",
        "has_branded":  "true",
        "notes":  "seen in legacy index"
    },
    {
        "clip_id":  "13|2025-10-04|TSC|FC_Tulsa_Black|BUILD_UP_PLAY|1290.00|1306",
        "index":  13,
        "date":  "2025-10-04",
        "homeTeam":  "TSC",
        "awayTeam":  "FC_Tulsa_Black",
        "label":  "BUILD_UP_PLAY",
        "tStart":  1290,
        "tEnd":  1306,
        "duration_sec":  16,
        "orientation":  "portrait",
        "hasDebug":  false,
        "hasFinal":  true,
        "root_dir":  "C:\\Users\\scott\\soccer-video\\out\\autoframe_work\\cinematic\\013__2025-10-04__TSC_vs_FC_Tulsa_Black__BUILD_UP_PLAY__t1290.00-t1306.00_portrait_FINAL",
        "proxy_path":  "C:\\Users\\scott\\soccer-video\\out\\autoframe_work\\cinematic\\013__2025-10-04__TSC_vs_FC_Tulsa_Black__BUILD_UP_PLAY__t1290.00-t1306.00_portrait_FINAL\\proxy.mp4",
        "trf_path":  "C:\\Users\\scott\\soccer-video\\out\\autoframe_work\\cinematic\\013__2025-10-04__TSC_vs_FC_Tulsa_Black__BUILD_UP_PLAY__t1290.00-t1306.00_portrait_FINAL\\follow\\transforms.trf",
        "stabilized_path":  "C:\\Users\\scott\\soccer-video\\out\\autoframe_work\\cinematic\\013__2025-10-04__TSC_vs_FC_Tulsa_Black__BUILD_UP_PLAY__t1290.00-t1306.00_portrait_FINAL\\follow\\stabilized.mp4",
        "branded_matches":  "C:\\Users\\scott\\soccer-video\\out\\portrait_reels\\branded\\001__2025-10-04__TSC_vs_FC_Tulsa_Black__DRIBBLING__t387.00-t412.00_portrait_BRAND.mp4;C:\\Users\\scott\\soccer-video\\out\\portrait_reels\\branded\\001__2025-10-04__TSC_vs_FC_Tulsa_Black__DRIBBLING__t387.00-t412.00_portrait_POST.mp4;C:\\Users\\scott\\soccer-video\\out\\portrait_reels\\branded\\002__2025-10-04__TSC_vs_FC_Tulsa_Black__BUILD_UP__t421.00-t449.00_portrait_POST.mp4;C:\\Users\\scott\\soccer-video\\out\\portrait_reels\\branded\\003__2025-10-04__TSC_vs_FC_Tulsa_Black__BUILD_UP__t458.00-t487.00_portrait_POST.mp4;C:\\Users\\scott\\soccer-video\\out\\portrait_reels\\branded\\004__2025-10-04__TSC_vs_FC_Tulsa_Black__BUILD_UP__t495.00-t513.00_portrait_POST.mp4;C:\\Users\\scott\\soccer-video\\out\\portrait_reels\\branded\\005__2025-10-04__TSC_vs_FC_Tulsa_Black__SHOT__t600.00-t607.00_portrait_POST.mp4;C:\\Users\\scott\\soccer-video\\out\\portrait_reels\\branded\\006__2025-10-04__TSC_vs_FC_Tulsa_Black__BUILD_UP_GOAL__t674.00-t717.00_portrait_POST.mp4;C:\\Users\\scott\\soccer-video\\out\\portrait_reels\\branded\\007__2025-10-04__TSC_vs_FC_Tulsa_Black__BUILD_UP_SHOT__t767.00-t785.00_portrait_POST.mp4;C:\\Users\\scott\\soccer-video\\out\\portrait_reels\\branded\\008__2025-10-04__TSC_vs_FC_Tulsa_Black__BUILD_UP_SHOT__t1025.00-t1040.00_portrait_POST.mp4;C:\\Users\\scott\\soccer-video\\out\\portrait_reels\\branded\\009__2025-10-04__TSC_vs_FC_Tulsa_Black__PRESSURE_SHOT__t1046.00-t1057.00_portrait_POST.mp4;C:\\Users\\scott\\soccer-video\\out\\portrait_reels\\branded\\010__2025-10-04__TSC_vs_FC_Tulsa_Black__BUILD_UP_SHOT__t1058.00-t1080.00_portrait_POST.mp4;C:\\Users\\scott\\soccer-video\\out\\portrait_reels\\branded\\011__2025-10-04__TSC_vs_FC_Tulsa_Black__BUILD_UP_SHOT__t1198.00-t1222.00_portrait_POST.mp4;C:\\Users\\scott\\soccer-video\\out\\portrait_reels\\branded\\012__2025-10-04__TSC_vs_FC_Tulsa_Black__PRESSURE_GOAL__t1239.00-t1253.00_portrait_POST.mp4;C:\\Users\\scott\\soccer-video\\out\\portrait_reels\\branded\\013__2025-10-04__TSC_vs_FC_Tulsa_Black__BUILD_UP_PLAY__t1290.00-t1306.00_portrait_POST.mp4;C:\\Users\\scott\\soccer-video\\out\\portrait_reels\\branded\\014__2025-10-04__TSC_vs_FC_Tulsa_Black__SHOT__t1626.00-t1637.00_portrait_POST.mp4;C:\\Users\\scott\\soccer-video\\out\\portrait_reels\\branded\\015__2025-10-04__TSC_vs_FC_Tulsa_Black__BUILD_UP_SHOT__t1705.00-t1721.00_portrait_POST.mp4",
        "proxy_exists":  "true",
        "trf_exists":  "true",
        "stabilized_exists":  "true",
        "has_branded":  "true",
        "notes":  "seen in legacy index"
    },
    {
        "clip_id":  "12|2025-10-04|TSC|FC_Tulsa_Black|PRESSURE_GOAL|1239.00|1253",
        "index":  12,
        "date":  "2025-10-04",
        "homeTeam":  "TSC",
        "awayTeam":  "FC_Tulsa_Black",
        "label":  "PRESSURE_GOAL",
        "tStart":  1239,
        "tEnd":  1253,
        "duration_sec":  14,
        "orientation":  "portrait",
        "hasDebug":  false,
        "hasFinal":  true,
        "root_dir":  "C:\\Users\\scott\\soccer-video\\out\\autoframe_work\\cinematic\\012__2025-10-04__TSC_vs_FC_Tulsa_Black__PRESSURE_GOAL__t1239.00-t1253.00_portrait_FINAL",
        "proxy_path":  "C:\\Users\\scott\\soccer-video\\out\\autoframe_work\\cinematic\\012__2025-10-04__TSC_vs_FC_Tulsa_Black__PRESSURE_GOAL__t1239.00-t1253.00_portrait_FINAL\\proxy.mp4",
        "trf_path":  "C:\\Users\\scott\\soccer-video\\out\\autoframe_work\\cinematic\\012__2025-10-04__TSC_vs_FC_Tulsa_Black__PRESSURE_GOAL__t1239.00-t1253.00_portrait_FINAL\\follow\\transforms.trf",
        "stabilized_path":  "C:\\Users\\scott\\soccer-video\\out\\autoframe_work\\cinematic\\012__2025-10-04__TSC_vs_FC_Tulsa_Black__PRESSURE_GOAL__t1239.00-t1253.00_portrait_FINAL\\follow\\stabilized.mp4",
        "branded_matches":  "C:\\Users\\scott\\soccer-video\\out\\portrait_reels\\branded\\001__2025-10-04__TSC_vs_FC_Tulsa_Black__DRIBBLING__t387.00-t412.00_portrait_BRAND.mp4;C:\\Users\\scott\\soccer-video\\out\\portrait_reels\\branded\\001__2025-10-04__TSC_vs_FC_Tulsa_Black__DRIBBLING__t387.00-t412.00_portrait_POST.mp4;C:\\Users\\scott\\soccer-video\\out\\portrait_reels\\branded\\002__2025-10-04__TSC_vs_FC_Tulsa_Black__BUILD_UP__t421.00-t449.00_portrait_POST.mp4;C:\\Users\\scott\\soccer-video\\out\\portrait_reels\\branded\\003__2025-10-04__TSC_vs_FC_Tulsa_Black__BUILD_UP__t458.00-t487.00_portrait_POST.mp4;C:\\Users\\scott\\soccer-video\\out\\portrait_reels\\branded\\004__2025-10-04__TSC_vs_FC_Tulsa_Black__BUILD_UP__t495.00-t513.00_portrait_POST.mp4;C:\\Users\\scott\\soccer-video\\out\\portrait_reels\\branded\\005__2025-10-04__TSC_vs_FC_Tulsa_Black__SHOT__t600.00-t607.00_portrait_POST.mp4;C:\\Users\\scott\\soccer-video\\out\\portrait_reels\\branded\\006__2025-10-04__TSC_vs_FC_Tulsa_Black__BUILD_UP_GOAL__t674.00-t717.00_portrait_POST.mp4;C:\\Users\\scott\\soccer-video\\out\\portrait_reels\\branded\\007__2025-10-04__TSC_vs_FC_Tulsa_Black__BUILD_UP_SHOT__t767.00-t785.00_portrait_POST.mp4;C:\\Users\\scott\\soccer-video\\out\\portrait_reels\\branded\\008__2025-10-04__TSC_vs_FC_Tulsa_Black__BUILD_UP_SHOT__t1025.00-t1040.00_portrait_POST.mp4;C:\\Users\\scott\\soccer-video\\out\\portrait_reels\\branded\\009__2025-10-04__TSC_vs_FC_Tulsa_Black__PRESSURE_SHOT__t1046.00-t1057.00_portrait_POST.mp4;C:\\Users\\scott\\soccer-video\\out\\portrait_reels\\branded\\010__2025-10-04__TSC_vs_FC_Tulsa_Black__BUILD_UP_SHOT__t1058.00-t1080.00_portrait_POST.mp4;C:\\Users\\scott\\soccer-video\\out\\portrait_reels\\branded\\011__2025-10-04__TSC_vs_FC_Tulsa_Black__BUILD_UP_SHOT__t1198.00-t1222.00_portrait_POST.mp4;C:\\Users\\scott\\soccer-video\\out\\portrait_reels\\branded\\012__2025-10-04__TSC_vs_FC_Tulsa_Black__PRESSURE_GOAL__t1239.00-t1253.00_portrait_POST.mp4;C:\\Users\\scott\\soccer-video\\out\\portrait_reels\\branded\\013__2025-10-04__TSC_vs_FC_Tulsa_Black__BUILD_UP_PLAY__t1290.00-t1306.00_portrait_POST.mp4;C:\\Users\\scott\\soccer-video\\out\\portrait_reels\\branded\\014__2025-10-04__TSC_vs_FC_Tulsa_Black__SHOT__t1626.00-t1637.00_portrait_POST.mp4;C:\\Users\\scott\\soccer-video\\out\\portrait_reels\\branded\\015__2025-10-04__TSC_vs_FC_Tulsa_Black__BUILD_UP_SHOT__t1705.00-t1721.00_portrait_POST.mp4",
        "proxy_exists":  "true",
        "trf_exists":  "true",
        "stabilized_exists":  "true",
        "has_branded":  "true",
        "notes":  "seen in legacy index"
    },
    {
        "clip_id":  "5|2025-10-04|TSC|FC_Tulsa_Black|SHOT|600.00|607",
        "index":  5,
        "date":  "2025-10-04",
        "homeTeam":  "TSC",
        "awayTeam":  "FC_Tulsa_Black",
        "label":  "SHOT",
        "tStart":  600,
        "tEnd":  607,
        "duration_sec":  7,
        "orientation":  "portrait",
        "hasDebug":  false,
        "hasFinal":  true,
        "root_dir":  "C:\\Users\\scott\\soccer-video\\out\\autoframe_work\\cinematic\\005__2025-10-04__TSC_vs_FC_Tulsa_Black__SHOT__t600.00-t607.00_portrait_FINAL",
        "proxy_path":  "C:\\Users\\scott\\soccer-video\\out\\autoframe_work\\cinematic\\005__2025-10-04__TSC_vs_FC_Tulsa_Black__SHOT__t600.00-t607.00_portrait_FINAL\\proxy.mp4",
        "trf_path":  "C:\\Users\\scott\\soccer-video\\out\\autoframe_work\\cinematic\\005__2025-10-04__TSC_vs_FC_Tulsa_Black__SHOT__t600.00-t607.00_portrait_FINAL\\follow\\transforms.trf",
        "stabilized_path":  "C:\\Users\\scott\\soccer-video\\out\\autoframe_work\\cinematic\\005__2025-10-04__TSC_vs_FC_Tulsa_Black__SHOT__t600.00-t607.00_portrait_FINAL\\follow\\stabilized.mp4",
        "branded_matches":  "C:\\Users\\scott\\soccer-video\\out\\portrait_reels\\branded\\001__2025-10-04__TSC_vs_FC_Tulsa_Black__DRIBBLING__t387.00-t412.00_portrait_BRAND.mp4;C:\\Users\\scott\\soccer-video\\out\\portrait_reels\\branded\\001__2025-10-04__TSC_vs_FC_Tulsa_Black__DRIBBLING__t387.00-t412.00_portrait_POST.mp4;C:\\Users\\scott\\soccer-video\\out\\portrait_reels\\branded\\002__2025-10-04__TSC_vs_FC_Tulsa_Black__BUILD_UP__t421.00-t449.00_portrait_POST.mp4;C:\\Users\\scott\\soccer-video\\out\\portrait_reels\\branded\\003__2025-10-04__TSC_vs_FC_Tulsa_Black__BUILD_UP__t458.00-t487.00_portrait_POST.mp4;C:\\Users\\scott\\soccer-video\\out\\portrait_reels\\branded\\004__2025-10-04__TSC_vs_FC_Tulsa_Black__BUILD_UP__t495.00-t513.00_portrait_POST.mp4;C:\\Users\\scott\\soccer-video\\out\\portrait_reels\\branded\\005__2025-10-04__TSC_vs_FC_Tulsa_Black__SHOT__t600.00-t607.00_portrait_POST.mp4;C:\\Users\\scott\\soccer-video\\out\\portrait_reels\\branded\\006__2025-10-04__TSC_vs_FC_Tulsa_Black__BUILD_UP_GOAL__t674.00-t717.00_portrait_POST.mp4;C:\\Users\\scott\\soccer-video\\out\\portrait_reels\\branded\\007__2025-10-04__TSC_vs_FC_Tulsa_Black__BUILD_UP_SHOT__t767.00-t785.00_portrait_POST.mp4;C:\\Users\\scott\\soccer-video\\out\\portrait_reels\\branded\\008__2025-10-04__TSC_vs_FC_Tulsa_Black__BUILD_UP_SHOT__t1025.00-t1040.00_portrait_POST.mp4;C:\\Users\\scott\\soccer-video\\out\\portrait_reels\\branded\\009__2025-10-04__TSC_vs_FC_Tulsa_Black__PRESSURE_SHOT__t1046.00-t1057.00_portrait_POST.mp4;C:\\Users\\scott\\soccer-video\\out\\portrait_reels\\branded\\010__2025-10-04__TSC_vs_FC_Tulsa_Black__BUILD_UP_SHOT__t1058.00-t1080.00_portrait_POST.mp4;C:\\Users\\scott\\soccer-video\\out\\portrait_reels\\branded\\011__2025-10-04__TSC_vs_FC_Tulsa_Black__BUILD_UP_SHOT__t1198.00-t1222.00_portrait_POST.mp4;C:\\Users\\scott\\soccer-video\\out\\portrait_reels\\branded\\012__2025-10-04__TSC_vs_FC_Tulsa_Black__PRESSURE_GOAL__t1239.00-t1253.00_portrait_POST.mp4;C:\\Users\\scott\\soccer-video\\out\\portrait_reels\\branded\\013__2025-10-04__TSC_vs_FC_Tulsa_Black__BUILD_UP_PLAY__t1290.00-t1306.00_portrait_POST.mp4;C:\\Users\\scott\\soccer-video\\out\\portrait_reels\\branded\\014__2025-10-04__TSC_vs_FC_Tulsa_Black__SHOT__t1626.00-t1637.00_portrait_POST.mp4;C:\\Users\\scott\\soccer-video\\out\\portrait_reels\\branded\\015__2025-10-04__TSC_vs_FC_Tulsa_Black__BUILD_UP_SHOT__t1705.00-t1721.00_portrait_POST.mp4",
        "proxy_exists":  "true",
        "trf_exists":  "true",
        "stabilized_exists":  "true",
        "has_branded":  "true",
        "notes":  "seen in legacy index"
    },
    {
        "clip_id":  "3|2025-10-04|TSC|FC_Tulsa_Black|BUILD_UP|458.00|487",
        "index":  3,
        "date":  "2025-10-04",
        "homeTeam":  "TSC",
        "awayTeam":  "FC_Tulsa_Black",
        "label":  "BUILD_UP",
        "tStart":  458,
        "tEnd":  487,
        "duration_sec":  29,
        "orientation":  "portrait",
        "hasDebug":  false,
        "hasFinal":  true,
        "root_dir":  "C:\\Users\\scott\\soccer-video\\out\\autoframe_work\\cinematic\\003__2025-10-04__TSC_vs_FC_Tulsa_Black__BUILD_UP__t458.00-t487.00_portrait_FINAL",
        "proxy_path":  "C:\\Users\\scott\\soccer-video\\out\\autoframe_work\\cinematic\\003__2025-10-04__TSC_vs_FC_Tulsa_Black__BUILD_UP__t458.00-t487.00_portrait_FINAL\\proxy.mp4",
        "trf_path":  "C:\\Users\\scott\\soccer-video\\out\\autoframe_work\\cinematic\\003__2025-10-04__TSC_vs_FC_Tulsa_Black__BUILD_UP__t458.00-t487.00_portrait_FINAL\\follow\\transforms.trf",
        "stabilized_path":  "C:\\Users\\scott\\soccer-video\\out\\autoframe_work\\cinematic\\003__2025-10-04__TSC_vs_FC_Tulsa_Black__BUILD_UP__t458.00-t487.00_portrait_FINAL\\follow\\stabilized.mp4",
        "branded_matches":  "C:\\Users\\scott\\soccer-video\\out\\portrait_reels\\branded\\001__2025-10-04__TSC_vs_FC_Tulsa_Black__DRIBBLING__t387.00-t412.00_portrait_BRAND.mp4;C:\\Users\\scott\\soccer-video\\out\\portrait_reels\\branded\\001__2025-10-04__TSC_vs_FC_Tulsa_Black__DRIBBLING__t387.00-t412.00_portrait_POST.mp4;C:\\Users\\scott\\soccer-video\\out\\portrait_reels\\branded\\002__2025-10-04__TSC_vs_FC_Tulsa_Black__BUILD_UP__t421.00-t449.00_portrait_POST.mp4;C:\\Users\\scott\\soccer-video\\out\\portrait_reels\\branded\\003__2025-10-04__TSC_vs_FC_Tulsa_Black__BUILD_UP__t458.00-t487.00_portrait_POST.mp4;C:\\Users\\scott\\soccer-video\\out\\portrait_reels\\branded\\004__2025-10-04__TSC_vs_FC_Tulsa_Black__BUILD_UP__t495.00-t513.00_portrait_POST.mp4;C:\\Users\\scott\\soccer-video\\out\\portrait_reels\\branded\\005__2025-10-04__TSC_vs_FC_Tulsa_Black__SHOT__t600.00-t607.00_portrait_POST.mp4;C:\\Users\\scott\\soccer-video\\out\\portrait_reels\\branded\\006__2025-10-04__TSC_vs_FC_Tulsa_Black__BUILD_UP_GOAL__t674.00-t717.00_portrait_POST.mp4;C:\\Users\\scott\\soccer-video\\out\\portrait_reels\\branded\\007__2025-10-04__TSC_vs_FC_Tulsa_Black__BUILD_UP_SHOT__t767.00-t785.00_portrait_POST.mp4;C:\\Users\\scott\\soccer-video\\out\\portrait_reels\\branded\\008__2025-10-04__TSC_vs_FC_Tulsa_Black__BUILD_UP_SHOT__t1025.00-t1040.00_portrait_POST.mp4;C:\\Users\\scott\\soccer-video\\out\\portrait_reels\\branded\\009__2025-10-04__TSC_vs_FC_Tulsa_Black__PRESSURE_SHOT__t1046.00-t1057.00_portrait_POST.mp4;C:\\Users\\scott\\soccer-video\\out\\portrait_reels\\branded\\010__2025-10-04__TSC_vs_FC_Tulsa_Black__BUILD_UP_SHOT__t1058.00-t1080.00_portrait_POST.mp4;C:\\Users\\scott\\soccer-video\\out\\portrait_reels\\branded\\011__2025-10-04__TSC_vs_FC_Tulsa_Black__BUILD_UP_SHOT__t1198.00-t1222.00_portrait_POST.mp4;C:\\Users\\scott\\soccer-video\\out\\portrait_reels\\branded\\012__2025-10-04__TSC_vs_FC_Tulsa_Black__PRESSURE_GOAL__t1239.00-t1253.00_portrait_POST.mp4;C:\\Users\\scott\\soccer-video\\out\\portrait_reels\\branded\\013__2025-10-04__TSC_vs_FC_Tulsa_Black__BUILD_UP_PLAY__t1290.00-t1306.00_portrait_POST.mp4;C:\\Users\\scott\\soccer-video\\out\\portrait_reels\\branded\\014__2025-10-04__TSC_vs_FC_Tulsa_Black__SHOT__t1626.00-t1637.00_portrait_POST.mp4;C:\\Users\\scott\\soccer-video\\out\\portrait_reels\\branded\\015__2025-10-04__TSC_vs_FC_Tulsa_Black__BUILD_UP_SHOT__t1705.00-t1721.00_portrait_POST.mp4",
        "proxy_exists":  "true",
        "trf_exists":  "true",
        "stabilized_exists":  "true",
        "has_branded":  "true",
        "notes":  "seen in legacy index"
    },
    {
        "clip_id":  "5|2025-09-13|TSC|NEOFC|CORNER|417.90|431.60",
        "index":  5,
        "date":  "2025-09-13",
        "homeTeam":  "TSC",
        "awayTeam":  "NEOFC",
        "label":  "CORNER",
        "tStart":  417.9,
        "tEnd":  431.6,
        "duration_sec":  13.7,
        "orientation":  "portrait",
        "hasDebug":  true,
        "hasFinal":  true,
        "root_dir":  "C:\\Users\\scott\\soccer-video\\out\\autoframe_work\\cinematic\\005__2025-09-13__TSC_vs_NEOFC__CORNER__t417.90-t431.60.__DEBUG_FINAL_portrait_FINAL",
        "proxy_path":  "C:\\Users\\scott\\soccer-video\\out\\autoframe_work\\cinematic\\005__2025-09-13__TSC_vs_NEOFC__CORNER__t417.90-t431.60.__DEBUG_FINAL_portrait_FINAL\\proxy.mp4",
        "trf_path":  "C:\\Users\\scott\\soccer-video\\out\\autoframe_work\\cinematic\\005__2025-09-13__TSC_vs_NEOFC__CORNER__t417.90-t431.60.__DEBUG_FINAL_portrait_FINAL\\follow\\transforms.trf",
        "stabilized_path":  "C:\\Users\\scott\\soccer-video\\out\\autoframe_work\\cinematic\\005__2025-09-13__TSC_vs_NEOFC__CORNER__t417.90-t431.60.__DEBUG_FINAL_portrait_FINAL\\follow\\stabilized.mp4",
        "branded_matches":  "C:\\Users\\scott\\soccer-video\\out\\portrait_reels\\branded\\001__2025-09-13__TSC_vs_NEOFC__SHOT__t155.50-t166.40_portrait_BRAND.mp4;C:\\Users\\scott\\soccer-video\\out\\portrait_reels\\branded\\001__2025-09-13__TSC_vs_NEOFC__SHOT__t155.50-t166.40_portrait_POST.mp4;C:\\Users\\scott\\soccer-video\\out\\portrait_reels\\branded\\002__2025-09-13__TSC_vs_NEOFC__GOAL__t180.80-t191.20_portrait_POST.mp4;C:\\Users\\scott\\soccer-video\\out\\portrait_reels\\branded\\003__2025-09-13__TSC_vs_NEOFC__BUILD_UP__t224.80-t248.70_portrait_POST.mp4;C:\\Users\\scott\\soccer-video\\out\\portrait_reels\\branded\\004__2025-09-13__TSC_vs_NEOFC__GOAL__t266.50-t283.10_portrait_POST.mp4;C:\\Users\\scott\\soccer-video\\out\\portrait_reels\\branded\\005__2025-09-13__TSC_vs_NEOFC__CORNER__t417.90-t431.60_portrait_POST.mp4;C:\\Users\\scott\\soccer-video\\out\\portrait_reels\\branded\\006__2025-09-13__TSC_vs_NEOFC__DEFENSE__t699.30-t711.50_portrait_POST.mp4;C:\\Users\\scott\\soccer-video\\out\\portrait_reels\\branded\\007__2025-09-13__TSC_vs_NEOFC__DRIBBLING__t982.00-t987.90_portrait_POST.mp4;C:\\Users\\scott\\soccer-video\\out\\portrait_reels\\branded\\008__2025-09-13__TSC_vs_NEOFC__SHOT__t1247.80-t1259.20_portrait_POST.mp4;C:\\Users\\scott\\soccer-video\\out\\portrait_reels\\branded\\009__2025-09-13__TSC_vs_NEOFC__SHOT__t1420.40-t1438.20_portrait_POST.mp4;C:\\Users\\scott\\soccer-video\\out\\portrait_reels\\branded\\010__2025-09-13__TSC_vs_NEOFC__CROSS__t1541.10-t1547.90_portrait_POST.mp4;C:\\Users\\scott\\soccer-video\\out\\portrait_reels\\branded\\011__2025-09-13__TSC_vs_NEOFC__SHOTS__t1655.00-t1670.30_portrait_POST.mp4;C:\\Users\\scott\\soccer-video\\out\\portrait_reels\\branded\\012__2025-09-13__TSC_vs_NEOFC__GOAL__t1705.20-t1708.50_portrait_POST.mp4;C:\\Users\\scott\\soccer-video\\out\\portrait_reels\\branded\\013__2025-09-13__TSC_vs_NEOFC__GOAL__t1767.50-t1772.60_portrait_POST.mp4;C:\\Users\\scott\\soccer-video\\out\\portrait_reels\\branded\\014__2025-09-13__TSC_vs_NEOFC__GOAL__t1904.20-t1925.20_portrait_POST.mp4;C:\\Users\\scott\\soccer-video\\out\\portrait_reels\\branded\\015__2025-09-13__TSC_vs_NEOFC__DRIBBLING__t1972.50-t1980.70_portrait_POST.mp4;C:\\Users\\scott\\soccer-video\\out\\portrait_reels\\branded\\016__2025-09-13__TSC_vs_NEOFC__SHOT__t2029.90-t2039.50_portrait_POST.mp4;C:\\Users\\scott\\soccer-video\\out\\portrait_reels\\branded\\017__2025-09-13__TSC_vs_NEOFC__SHOT__t2284.90-t2298.20_portrait_POST.mp4;C:\\Users\\scott\\soccer-video\\out\\portrait_reels\\branded\\018__2025-09-13__TSC_vs_NEOFC__SHOT__t2419.50-t2425.60_portrait_POST.mp4;C:\\Users\\scott\\soccer-video\\out\\portrait_reels\\branded\\019__2025-09-13__TSC_vs_NEOFC__SHOT__t2633.00-t2638.10_portrait_POST.mp4;C:\\Users\\scott\\soccer-video\\out\\portrait_reels\\branded\\020__2025-09-13__TSC_vs_NEOFC__GOAL__t2816.60-t2831.80_portrait_POST.mp4;C:\\Users\\scott\\soccer-video\\out\\portrait_reels\\branded\\021__2025-09-13__TSC_vs_NEOFC__SHOT__t2860.70-t2873.00_portrait_POST.mp4;C:\\Users\\scott\\soccer-video\\out\\portrait_reels\\branded\\023__2025-09-13__TSC_vs_NEOFC__SHOT__t3098.90-t3108.80_portrait_POST.mp4",
        "proxy_exists":  "true",
        "trf_exists":  "true",
        "stabilized_exists":  "true",
        "has_branded":  "true",
        "notes":  "seen in legacy index"
    },
    {
        "clip_id":  "4|2025-10-04|TSC|FC_Tulsa_Black|BUILD_UP|495.00|513",
        "index":  4,
        "date":  "2025-10-04",
        "homeTeam":  "TSC",
        "awayTeam":  "FC_Tulsa_Black",
        "label":  "BUILD_UP",
        "tStart":  495,
        "tEnd":  513,
        "duration_sec":  18,
        "orientation":  "portrait",
        "hasDebug":  false,
        "hasFinal":  true,
        "root_dir":  "C:\\Users\\scott\\soccer-video\\out\\autoframe_work\\cinematic\\004__2025-10-04__TSC_vs_FC_Tulsa_Black__BUILD_UP__t495.00-t513.00_portrait_FINAL",
        "proxy_path":  "C:\\Users\\scott\\soccer-video\\out\\autoframe_work\\cinematic\\004__2025-10-04__TSC_vs_FC_Tulsa_Black__BUILD_UP__t495.00-t513.00_portrait_FINAL\\proxy.mp4",
        "trf_path":  "C:\\Users\\scott\\soccer-video\\out\\autoframe_work\\cinematic\\004__2025-10-04__TSC_vs_FC_Tulsa_Black__BUILD_UP__t495.00-t513.00_portrait_FINAL\\follow\\transforms.trf",
        "stabilized_path":  "C:\\Users\\scott\\soccer-video\\out\\autoframe_work\\cinematic\\004__2025-10-04__TSC_vs_FC_Tulsa_Black__BUILD_UP__t495.00-t513.00_portrait_FINAL\\follow\\stabilized.mp4",
        "branded_matches":  "C:\\Users\\scott\\soccer-video\\out\\portrait_reels\\branded\\001__2025-10-04__TSC_vs_FC_Tulsa_Black__DRIBBLING__t387.00-t412.00_portrait_BRAND.mp4;C:\\Users\\scott\\soccer-video\\out\\portrait_reels\\branded\\001__2025-10-04__TSC_vs_FC_Tulsa_Black__DRIBBLING__t387.00-t412.00_portrait_POST.mp4;C:\\Users\\scott\\soccer-video\\out\\portrait_reels\\branded\\002__2025-10-04__TSC_vs_FC_Tulsa_Black__BUILD_UP__t421.00-t449.00_portrait_POST.mp4;C:\\Users\\scott\\soccer-video\\out\\portrait_reels\\branded\\003__2025-10-04__TSC_vs_FC_Tulsa_Black__BUILD_UP__t458.00-t487.00_portrait_POST.mp4;C:\\Users\\scott\\soccer-video\\out\\portrait_reels\\branded\\004__2025-10-04__TSC_vs_FC_Tulsa_Black__BUILD_UP__t495.00-t513.00_portrait_POST.mp4;C:\\Users\\scott\\soccer-video\\out\\portrait_reels\\branded\\005__2025-10-04__TSC_vs_FC_Tulsa_Black__SHOT__t600.00-t607.00_portrait_POST.mp4;C:\\Users\\scott\\soccer-video\\out\\portrait_reels\\branded\\006__2025-10-04__TSC_vs_FC_Tulsa_Black__BUILD_UP_GOAL__t674.00-t717.00_portrait_POST.mp4;C:\\Users\\scott\\soccer-video\\out\\portrait_reels\\branded\\007__2025-10-04__TSC_vs_FC_Tulsa_Black__BUILD_UP_SHOT__t767.00-t785.00_portrait_POST.mp4;C:\\Users\\scott\\soccer-video\\out\\portrait_reels\\branded\\008__2025-10-04__TSC_vs_FC_Tulsa_Black__BUILD_UP_SHOT__t1025.00-t1040.00_portrait_POST.mp4;C:\\Users\\scott\\soccer-video\\out\\portrait_reels\\branded\\009__2025-10-04__TSC_vs_FC_Tulsa_Black__PRESSURE_SHOT__t1046.00-t1057.00_portrait_POST.mp4;C:\\Users\\scott\\soccer-video\\out\\portrait_reels\\branded\\010__2025-10-04__TSC_vs_FC_Tulsa_Black__BUILD_UP_SHOT__t1058.00-t1080.00_portrait_POST.mp4;C:\\Users\\scott\\soccer-video\\out\\portrait_reels\\branded\\011__2025-10-04__TSC_vs_FC_Tulsa_Black__BUILD_UP_SHOT__t1198.00-t1222.00_portrait_POST.mp4;C:\\Users\\scott\\soccer-video\\out\\portrait_reels\\branded\\012__2025-10-04__TSC_vs_FC_Tulsa_Black__PRESSURE_GOAL__t1239.00-t1253.00_portrait_POST.mp4;C:\\Users\\scott\\soccer-video\\out\\portrait_reels\\branded\\013__2025-10-04__TSC_vs_FC_Tulsa_Black__BUILD_UP_PLAY__t1290.00-t1306.00_portrait_POST.mp4;C:\\Users\\scott\\soccer-video\\out\\portrait_reels\\branded\\014__2025-10-04__TSC_vs_FC_Tulsa_Black__SHOT__t1626.00-t1637.00_portrait_POST.mp4;C:\\Users\\scott\\soccer-video\\out\\portrait_reels\\branded\\015__2025-10-04__TSC_vs_FC_Tulsa_Black__BUILD_UP_SHOT__t1705.00-t1721.00_portrait_POST.mp4",
        "proxy_exists":  "true",
        "trf_exists":  "true",
        "stabilized_exists":  "true",
        "has_branded":  "true",
        "notes":  "seen in legacy index"
    },
    {
        "clip_id":  "9|2025-10-04|TSC|FC_Tulsa_Black|PRESSURE_SHOT|1046.00|1057",
        "index":  9,
        "date":  "2025-10-04",
        "homeTeam":  "TSC",
        "awayTeam":  "FC_Tulsa_Black",
        "label":  "PRESSURE_SHOT",
        "tStart":  1046,
        "tEnd":  1057,
        "duration_sec":  11,
        "orientation":  "portrait",
        "hasDebug":  false,
        "hasFinal":  true,
        "root_dir":  "C:\\Users\\scott\\soccer-video\\out\\autoframe_work\\cinematic\\009__2025-10-04__TSC_vs_FC_Tulsa_Black__PRESSURE_SHOT__t1046.00-t1057.00_portrait_FINAL",
        "proxy_path":  "C:\\Users\\scott\\soccer-video\\out\\autoframe_work\\cinematic\\009__2025-10-04__TSC_vs_FC_Tulsa_Black__PRESSURE_SHOT__t1046.00-t1057.00_portrait_FINAL\\proxy.mp4",
        "trf_path":  "C:\\Users\\scott\\soccer-video\\out\\autoframe_work\\cinematic\\009__2025-10-04__TSC_vs_FC_Tulsa_Black__PRESSURE_SHOT__t1046.00-t1057.00_portrait_FINAL\\follow\\transforms.trf",
        "stabilized_path":  "C:\\Users\\scott\\soccer-video\\out\\autoframe_work\\cinematic\\009__2025-10-04__TSC_vs_FC_Tulsa_Black__PRESSURE_SHOT__t1046.00-t1057.00_portrait_FINAL\\follow\\stabilized.mp4",
        "branded_matches":  "C:\\Users\\scott\\soccer-video\\out\\portrait_reels\\branded\\001__2025-10-04__TSC_vs_FC_Tulsa_Black__DRIBBLING__t387.00-t412.00_portrait_BRAND.mp4;C:\\Users\\scott\\soccer-video\\out\\portrait_reels\\branded\\001__2025-10-04__TSC_vs_FC_Tulsa_Black__DRIBBLING__t387.00-t412.00_portrait_POST.mp4;C:\\Users\\scott\\soccer-video\\out\\portrait_reels\\branded\\002__2025-10-04__TSC_vs_FC_Tulsa_Black__BUILD_UP__t421.00-t449.00_portrait_POST.mp4;C:\\Users\\scott\\soccer-video\\out\\portrait_reels\\branded\\003__2025-10-04__TSC_vs_FC_Tulsa_Black__BUILD_UP__t458.00-t487.00_portrait_POST.mp4;C:\\Users\\scott\\soccer-video\\out\\portrait_reels\\branded\\004__2025-10-04__TSC_vs_FC_Tulsa_Black__BUILD_UP__t495.00-t513.00_portrait_POST.mp4;C:\\Users\\scott\\soccer-video\\out\\portrait_reels\\branded\\005__2025-10-04__TSC_vs_FC_Tulsa_Black__SHOT__t600.00-t607.00_portrait_POST.mp4;C:\\Users\\scott\\soccer-video\\out\\portrait_reels\\branded\\006__2025-10-04__TSC_vs_FC_Tulsa_Black__BUILD_UP_GOAL__t674.00-t717.00_portrait_POST.mp4;C:\\Users\\scott\\soccer-video\\out\\portrait_reels\\branded\\007__2025-10-04__TSC_vs_FC_Tulsa_Black__BUILD_UP_SHOT__t767.00-t785.00_portrait_POST.mp4;C:\\Users\\scott\\soccer-video\\out\\portrait_reels\\branded\\008__2025-10-04__TSC_vs_FC_Tulsa_Black__BUILD_UP_SHOT__t1025.00-t1040.00_portrait_POST.mp4;C:\\Users\\scott\\soccer-video\\out\\portrait_reels\\branded\\009__2025-10-04__TSC_vs_FC_Tulsa_Black__PRESSURE_SHOT__t1046.00-t1057.00_portrait_POST.mp4;C:\\Users\\scott\\soccer-video\\out\\portrait_reels\\branded\\010__2025-10-04__TSC_vs_FC_Tulsa_Black__BUILD_UP_SHOT__t1058.00-t1080.00_portrait_POST.mp4;C:\\Users\\scott\\soccer-video\\out\\portrait_reels\\branded\\011__2025-10-04__TSC_vs_FC_Tulsa_Black__BUILD_UP_SHOT__t1198.00-t1222.00_portrait_POST.mp4;C:\\Users\\scott\\soccer-video\\out\\portrait_reels\\branded\\012__2025-10-04__TSC_vs_FC_Tulsa_Black__PRESSURE_GOAL__t1239.00-t1253.00_portrait_POST.mp4;C:\\Users\\scott\\soccer-video\\out\\portrait_reels\\branded\\013__2025-10-04__TSC_vs_FC_Tulsa_Black__BUILD_UP_PLAY__t1290.00-t1306.00_portrait_POST.mp4;C:\\Users\\scott\\soccer-video\\out\\portrait_reels\\branded\\014__2025-10-04__TSC_vs_FC_Tulsa_Black__SHOT__t1626.00-t1637.00_portrait_POST.mp4;C:\\Users\\scott\\soccer-video\\out\\portrait_reels\\branded\\015__2025-10-04__TSC_vs_FC_Tulsa_Black__BUILD_UP_SHOT__t1705.00-t1721.00_portrait_POST.mp4",
        "proxy_exists":  "true",
        "trf_exists":  "true",
        "stabilized_exists":  "true",
        "has_branded":  "true",
        "notes":  "seen in legacy index"
    },
    {
        "clip_id":  "1|2025-09-13|TSC|NEOFC|SHOT|155.50|166.40",
        "index":  1,
        "date":  "2025-09-13",
        "homeTeam":  "TSC",
        "awayTeam":  "NEOFC",
        "label":  "SHOT",
        "tStart":  155.5,
        "tEnd":  166.4,
        "duration_sec":  10.9,
        "orientation":  "portrait",
        "hasDebug":  true,
        "hasFinal":  true,
        "root_dir":  "C:\\Users\\scott\\soccer-video\\out\\autoframe_work\\cinematic\\001__2025-09-13__TSC_vs_NEOFC__SHOT__t155.50-t166.40.__DEBUG_FINAL_portrait_FINAL",
        "proxy_path":  "C:\\Users\\scott\\soccer-video\\out\\autoframe_work\\cinematic\\001__2025-09-13__TSC_vs_NEOFC__SHOT__t155.50-t166.40.__DEBUG_FINAL_portrait_FINAL\\proxy.mp4",
        "trf_path":  "C:\\Users\\scott\\soccer-video\\out\\autoframe_work\\cinematic\\001__2025-09-13__TSC_vs_NEOFC__SHOT__t155.50-t166.40.__DEBUG_FINAL_portrait_FINAL\\follow\\transforms.trf",
        "stabilized_path":  "C:\\Users\\scott\\soccer-video\\out\\autoframe_work\\cinematic\\001__2025-09-13__TSC_vs_NEOFC__SHOT__t155.50-t166.40.__DEBUG_FINAL_portrait_FINAL\\follow\\stabilized.mp4",
        "branded_matches":  "C:\\Users\\scott\\soccer-video\\out\\portrait_reels\\branded\\001__2025-09-13__TSC_vs_NEOFC__SHOT__t155.50-t166.40_portrait_BRAND.mp4;C:\\Users\\scott\\soccer-video\\out\\portrait_reels\\branded\\001__2025-09-13__TSC_vs_NEOFC__SHOT__t155.50-t166.40_portrait_POST.mp4;C:\\Users\\scott\\soccer-video\\out\\portrait_reels\\branded\\002__2025-09-13__TSC_vs_NEOFC__GOAL__t180.80-t191.20_portrait_POST.mp4;C:\\Users\\scott\\soccer-video\\out\\portrait_reels\\branded\\003__2025-09-13__TSC_vs_NEOFC__BUILD_UP__t224.80-t248.70_portrait_POST.mp4;C:\\Users\\scott\\soccer-video\\out\\portrait_reels\\branded\\004__2025-09-13__TSC_vs_NEOFC__GOAL__t266.50-t283.10_portrait_POST.mp4;C:\\Users\\scott\\soccer-video\\out\\portrait_reels\\branded\\005__2025-09-13__TSC_vs_NEOFC__CORNER__t417.90-t431.60_portrait_POST.mp4;C:\\Users\\scott\\soccer-video\\out\\portrait_reels\\branded\\006__2025-09-13__TSC_vs_NEOFC__DEFENSE__t699.30-t711.50_portrait_POST.mp4;C:\\Users\\scott\\soccer-video\\out\\portrait_reels\\branded\\007__2025-09-13__TSC_vs_NEOFC__DRIBBLING__t982.00-t987.90_portrait_POST.mp4;C:\\Users\\scott\\soccer-video\\out\\portrait_reels\\branded\\008__2025-09-13__TSC_vs_NEOFC__SHOT__t1247.80-t1259.20_portrait_POST.mp4;C:\\Users\\scott\\soccer-video\\out\\portrait_reels\\branded\\009__2025-09-13__TSC_vs_NEOFC__SHOT__t1420.40-t1438.20_portrait_POST.mp4;C:\\Users\\scott\\soccer-video\\out\\portrait_reels\\branded\\010__2025-09-13__TSC_vs_NEOFC__CROSS__t1541.10-t1547.90_portrait_POST.mp4;C:\\Users\\scott\\soccer-video\\out\\portrait_reels\\branded\\011__2025-09-13__TSC_vs_NEOFC__SHOTS__t1655.00-t1670.30_portrait_POST.mp4;C:\\Users\\scott\\soccer-video\\out\\portrait_reels\\branded\\012__2025-09-13__TSC_vs_NEOFC__GOAL__t1705.20-t1708.50_portrait_POST.mp4;C:\\Users\\scott\\soccer-video\\out\\portrait_reels\\branded\\013__2025-09-13__TSC_vs_NEOFC__GOAL__t1767.50-t1772.60_portrait_POST.mp4;C:\\Users\\scott\\soccer-video\\out\\portrait_reels\\branded\\014__2025-09-13__TSC_vs_NEOFC__GOAL__t1904.20-t1925.20_portrait_POST.mp4;C:\\Users\\scott\\soccer-video\\out\\portrait_reels\\branded\\015__2025-09-13__TSC_vs_NEOFC__DRIBBLING__t1972.50-t1980.70_portrait_POST.mp4;C:\\Users\\scott\\soccer-video\\out\\portrait_reels\\branded\\016__2025-09-13__TSC_vs_NEOFC__SHOT__t2029.90-t2039.50_portrait_POST.mp4;C:\\Users\\scott\\soccer-video\\out\\portrait_reels\\branded\\017__2025-09-13__TSC_vs_NEOFC__SHOT__t2284.90-t2298.20_portrait_POST.mp4;C:\\Users\\scott\\soccer-video\\out\\portrait_reels\\branded\\018__2025-09-13__TSC_vs_NEOFC__SHOT__t2419.50-t2425.60_portrait_POST.mp4;C:\\Users\\scott\\soccer-video\\out\\portrait_reels\\branded\\019__2025-09-13__TSC_vs_NEOFC__SHOT__t2633.00-t2638.10_portrait_POST.mp4;C:\\Users\\scott\\soccer-video\\out\\portrait_reels\\branded\\020__2025-09-13__TSC_vs_NEOFC__GOAL__t2816.60-t2831.80_portrait_POST.mp4;C:\\Users\\scott\\soccer-video\\out\\portrait_reels\\branded\\021__2025-09-13__TSC_vs_NEOFC__SHOT__t2860.70-t2873.00_portrait_POST.mp4;C:\\Users\\scott\\soccer-video\\out\\portrait_reels\\branded\\023__2025-09-13__TSC_vs_NEOFC__SHOT__t3098.90-t3108.80_portrait_POST.mp4",
        "proxy_exists":  "true",
        "trf_exists":  "true",
        "stabilized_exists":  "true",
        "has_branded":  "true",
        "notes":  "seen in legacy index"
    },
    {
        "clip_id":  "14|2025-10-04|TSC|FC_Tulsa_Black|SHOT|1626.00|1637",
        "index":  14,
        "date":  "2025-10-04",
        "homeTeam":  "TSC",
        "awayTeam":  "FC_Tulsa_Black",
        "label":  "SHOT",
        "tStart":  1626,
        "tEnd":  1637,
        "duration_sec":  11,
        "orientation":  "portrait",
        "hasDebug":  false,
        "hasFinal":  true,
        "root_dir":  "C:\\Users\\scott\\soccer-video\\out\\autoframe_work\\cinematic\\014__2025-10-04__TSC_vs_FC_Tulsa_Black__SHOT__t1626.00-t1637.00_portrait_FINAL",
        "proxy_path":  "C:\\Users\\scott\\soccer-video\\out\\autoframe_work\\cinematic\\014__2025-10-04__TSC_vs_FC_Tulsa_Black__SHOT__t1626.00-t1637.00_portrait_FINAL\\proxy.mp4",
        "trf_path":  "C:\\Users\\scott\\soccer-video\\out\\autoframe_work\\cinematic\\014__2025-10-04__TSC_vs_FC_Tulsa_Black__SHOT__t1626.00-t1637.00_portrait_FINAL\\follow\\transforms.trf",
        "stabilized_path":  "C:\\Users\\scott\\soccer-video\\out\\autoframe_work\\cinematic\\014__2025-10-04__TSC_vs_FC_Tulsa_Black__SHOT__t1626.00-t1637.00_portrait_FINAL\\follow\\stabilized.mp4",
        "branded_matches":  "C:\\Users\\scott\\soccer-video\\out\\portrait_reels\\branded\\001__2025-10-04__TSC_vs_FC_Tulsa_Black__DRIBBLING__t387.00-t412.00_portrait_BRAND.mp4;C:\\Users\\scott\\soccer-video\\out\\portrait_reels\\branded\\001__2025-10-04__TSC_vs_FC_Tulsa_Black__DRIBBLING__t387.00-t412.00_portrait_POST.mp4;C:\\Users\\scott\\soccer-video\\out\\portrait_reels\\branded\\002__2025-10-04__TSC_vs_FC_Tulsa_Black__BUILD_UP__t421.00-t449.00_portrait_POST.mp4;C:\\Users\\scott\\soccer-video\\out\\portrait_reels\\branded\\003__2025-10-04__TSC_vs_FC_Tulsa_Black__BUILD_UP__t458.00-t487.00_portrait_POST.mp4;C:\\Users\\scott\\soccer-video\\out\\portrait_reels\\branded\\004__2025-10-04__TSC_vs_FC_Tulsa_Black__BUILD_UP__t495.00-t513.00_portrait_POST.mp4;C:\\Users\\scott\\soccer-video\\out\\portrait_reels\\branded\\005__2025-10-04__TSC_vs_FC_Tulsa_Black__SHOT__t600.00-t607.00_portrait_POST.mp4;C:\\Users\\scott\\soccer-video\\out\\portrait_reels\\branded\\006__2025-10-04__TSC_vs_FC_Tulsa_Black__BUILD_UP_GOAL__t674.00-t717.00_portrait_POST.mp4;C:\\Users\\scott\\soccer-video\\out\\portrait_reels\\branded\\007__2025-10-04__TSC_vs_FC_Tulsa_Black__BUILD_UP_SHOT__t767.00-t785.00_portrait_POST.mp4;C:\\Users\\scott\\soccer-video\\out\\portrait_reels\\branded\\008__2025-10-04__TSC_vs_FC_Tulsa_Black__BUILD_UP_SHOT__t1025.00-t1040.00_portrait_POST.mp4;C:\\Users\\scott\\soccer-video\\out\\portrait_reels\\branded\\009__2025-10-04__TSC_vs_FC_Tulsa_Black__PRESSURE_SHOT__t1046.00-t1057.00_portrait_POST.mp4;C:\\Users\\scott\\soccer-video\\out\\portrait_reels\\branded\\010__2025-10-04__TSC_vs_FC_Tulsa_Black__BUILD_UP_SHOT__t1058.00-t1080.00_portrait_POST.mp4;C:\\Users\\scott\\soccer-video\\out\\portrait_reels\\branded\\011__2025-10-04__TSC_vs_FC_Tulsa_Black__BUILD_UP_SHOT__t1198.00-t1222.00_portrait_POST.mp4;C:\\Users\\scott\\soccer-video\\out\\portrait_reels\\branded\\012__2025-10-04__TSC_vs_FC_Tulsa_Black__PRESSURE_GOAL__t1239.00-t1253.00_portrait_POST.mp4;C:\\Users\\scott\\soccer-video\\out\\portrait_reels\\branded\\013__2025-10-04__TSC_vs_FC_Tulsa_Black__BUILD_UP_PLAY__t1290.00-t1306.00_portrait_POST.mp4;C:\\Users\\scott\\soccer-video\\out\\portrait_reels\\branded\\014__2025-10-04__TSC_vs_FC_Tulsa_Black__SHOT__t1626.00-t1637.00_portrait_POST.mp4;C:\\Users\\scott\\soccer-video\\out\\portrait_reels\\branded\\015__2025-10-04__TSC_vs_FC_Tulsa_Black__BUILD_UP_SHOT__t1705.00-t1721.00_portrait_POST.mp4",
        "proxy_exists":  "true",
        "trf_exists":  "true",
        "stabilized_exists":  "true",
        "has_branded":  "true",
        "notes":  "seen in legacy index"
    },
    {
        "clip_id":  "10|2025-10-04|TSC|FC_Tulsa_Black|BUILD_UP_SHOT|1058.00|1080",
        "index":  10,
        "date":  "2025-10-04",
        "homeTeam":  "TSC",
        "awayTeam":  "FC_Tulsa_Black",
        "label":  "BUILD_UP_SHOT",
        "tStart":  1058,
        "tEnd":  1080,
        "duration_sec":  22,
        "orientation":  "portrait",
        "hasDebug":  false,
        "hasFinal":  true,
        "root_dir":  "C:\\Users\\scott\\soccer-video\\out\\autoframe_work\\cinematic\\010__2025-10-04__TSC_vs_FC_Tulsa_Black__BUILD_UP_SHOT__t1058.00-t1080.00_portrait_FINAL",
        "proxy_path":  "C:\\Users\\scott\\soccer-video\\out\\autoframe_work\\cinematic\\010__2025-10-04__TSC_vs_FC_Tulsa_Black__BUILD_UP_SHOT__t1058.00-t1080.00_portrait_FINAL\\proxy.mp4",
        "trf_path":  "C:\\Users\\scott\\soccer-video\\out\\autoframe_work\\cinematic\\010__2025-10-04__TSC_vs_FC_Tulsa_Black__BUILD_UP_SHOT__t1058.00-t1080.00_portrait_FINAL\\follow\\transforms.trf",
        "stabilized_path":  "C:\\Users\\scott\\soccer-video\\out\\autoframe_work\\cinematic\\010__2025-10-04__TSC_vs_FC_Tulsa_Black__BUILD_UP_SHOT__t1058.00-t1080.00_portrait_FINAL\\follow\\stabilized.mp4",
        "branded_matches":  "C:\\Users\\scott\\soccer-video\\out\\portrait_reels\\branded\\001__2025-10-04__TSC_vs_FC_Tulsa_Black__DRIBBLING__t387.00-t412.00_portrait_BRAND.mp4;C:\\Users\\scott\\soccer-video\\out\\portrait_reels\\branded\\001__2025-10-04__TSC_vs_FC_Tulsa_Black__DRIBBLING__t387.00-t412.00_portrait_POST.mp4;C:\\Users\\scott\\soccer-video\\out\\portrait_reels\\branded\\002__2025-10-04__TSC_vs_FC_Tulsa_Black__BUILD_UP__t421.00-t449.00_portrait_POST.mp4;C:\\Users\\scott\\soccer-video\\out\\portrait_reels\\branded\\003__2025-10-04__TSC_vs_FC_Tulsa_Black__BUILD_UP__t458.00-t487.00_portrait_POST.mp4;C:\\Users\\scott\\soccer-video\\out\\portrait_reels\\branded\\004__2025-10-04__TSC_vs_FC_Tulsa_Black__BUILD_UP__t495.00-t513.00_portrait_POST.mp4;C:\\Users\\scott\\soccer-video\\out\\portrait_reels\\branded\\005__2025-10-04__TSC_vs_FC_Tulsa_Black__SHOT__t600.00-t607.00_portrait_POST.mp4;C:\\Users\\scott\\soccer-video\\out\\portrait_reels\\branded\\006__2025-10-04__TSC_vs_FC_Tulsa_Black__BUILD_UP_GOAL__t674.00-t717.00_portrait_POST.mp4;C:\\Users\\scott\\soccer-video\\out\\portrait_reels\\branded\\007__2025-10-04__TSC_vs_FC_Tulsa_Black__BUILD_UP_SHOT__t767.00-t785.00_portrait_POST.mp4;C:\\Users\\scott\\soccer-video\\out\\portrait_reels\\branded\\008__2025-10-04__TSC_vs_FC_Tulsa_Black__BUILD_UP_SHOT__t1025.00-t1040.00_portrait_POST.mp4;C:\\Users\\scott\\soccer-video\\out\\portrait_reels\\branded\\009__2025-10-04__TSC_vs_FC_Tulsa_Black__PRESSURE_SHOT__t1046.00-t1057.00_portrait_POST.mp4;C:\\Users\\scott\\soccer-video\\out\\portrait_reels\\branded\\010__2025-10-04__TSC_vs_FC_Tulsa_Black__BUILD_UP_SHOT__t1058.00-t1080.00_portrait_POST.mp4;C:\\Users\\scott\\soccer-video\\out\\portrait_reels\\branded\\011__2025-10-04__TSC_vs_FC_Tulsa_Black__BUILD_UP_SHOT__t1198.00-t1222.00_portrait_POST.mp4;C:\\Users\\scott\\soccer-video\\out\\portrait_reels\\branded\\012__2025-10-04__TSC_vs_FC_Tulsa_Black__PRESSURE_GOAL__t1239.00-t1253.00_portrait_POST.mp4;C:\\Users\\scott\\soccer-video\\out\\portrait_reels\\branded\\013__2025-10-04__TSC_vs_FC_Tulsa_Black__BUILD_UP_PLAY__t1290.00-t1306.00_portrait_POST.mp4;C:\\Users\\scott\\soccer-video\\out\\portrait_reels\\branded\\014__2025-10-04__TSC_vs_FC_Tulsa_Black__SHOT__t1626.00-t1637.00_portrait_POST.mp4;C:\\Users\\scott\\soccer-video\\out\\portrait_reels\\branded\\015__2025-10-04__TSC_vs_FC_Tulsa_Black__BUILD_UP_SHOT__t1705.00-t1721.00_portrait_POST.mp4",
        "proxy_exists":  "true",
        "trf_exists":  "true",
        "stabilized_exists":  "true",
        "has_branded":  "true",
        "notes":  "seen in legacy index"
    },
    {
        "clip_id":  "8|2025-10-04|TSC|FC_Tulsa_Black|BUILD_UP_SHOT|1025.00|1040",
        "index":  8,
        "date":  "2025-10-04",
        "homeTeam":  "TSC",
        "awayTeam":  "FC_Tulsa_Black",
        "label":  "BUILD_UP_SHOT",
        "tStart":  1025,
        "tEnd":  1040,
        "duration_sec":  15,
        "orientation":  "portrait",
        "hasDebug":  false,
        "hasFinal":  true,
        "root_dir":  "C:\\Users\\scott\\soccer-video\\out\\autoframe_work\\cinematic\\008__2025-10-04__TSC_vs_FC_Tulsa_Black__BUILD_UP_SHOT__t1025.00-t1040.00_portrait_FINAL",
        "proxy_path":  "C:\\Users\\scott\\soccer-video\\out\\autoframe_work\\cinematic\\008__2025-10-04__TSC_vs_FC_Tulsa_Black__BUILD_UP_SHOT__t1025.00-t1040.00_portrait_FINAL\\proxy.mp4",
        "trf_path":  "C:\\Users\\scott\\soccer-video\\out\\autoframe_work\\cinematic\\008__2025-10-04__TSC_vs_FC_Tulsa_Black__BUILD_UP_SHOT__t1025.00-t1040.00_portrait_FINAL\\follow\\transforms.trf",
        "stabilized_path":  "C:\\Users\\scott\\soccer-video\\out\\autoframe_work\\cinematic\\008__2025-10-04__TSC_vs_FC_Tulsa_Black__BUILD_UP_SHOT__t1025.00-t1040.00_portrait_FINAL\\follow\\stabilized.mp4",
        "branded_matches":  "C:\\Users\\scott\\soccer-video\\out\\portrait_reels\\branded\\001__2025-10-04__TSC_vs_FC_Tulsa_Black__DRIBBLING__t387.00-t412.00_portrait_BRAND.mp4;C:\\Users\\scott\\soccer-video\\out\\portrait_reels\\branded\\001__2025-10-04__TSC_vs_FC_Tulsa_Black__DRIBBLING__t387.00-t412.00_portrait_POST.mp4;C:\\Users\\scott\\soccer-video\\out\\portrait_reels\\branded\\002__2025-10-04__TSC_vs_FC_Tulsa_Black__BUILD_UP__t421.00-t449.00_portrait_POST.mp4;C:\\Users\\scott\\soccer-video\\out\\portrait_reels\\branded\\003__2025-10-04__TSC_vs_FC_Tulsa_Black__BUILD_UP__t458.00-t487.00_portrait_POST.mp4;C:\\Users\\scott\\soccer-video\\out\\portrait_reels\\branded\\004__2025-10-04__TSC_vs_FC_Tulsa_Black__BUILD_UP__t495.00-t513.00_portrait_POST.mp4;C:\\Users\\scott\\soccer-video\\out\\portrait_reels\\branded\\005__2025-10-04__TSC_vs_FC_Tulsa_Black__SHOT__t600.00-t607.00_portrait_POST.mp4;C:\\Users\\scott\\soccer-video\\out\\portrait_reels\\branded\\006__2025-10-04__TSC_vs_FC_Tulsa_Black__BUILD_UP_GOAL__t674.00-t717.00_portrait_POST.mp4;C:\\Users\\scott\\soccer-video\\out\\portrait_reels\\branded\\007__2025-10-04__TSC_vs_FC_Tulsa_Black__BUILD_UP_SHOT__t767.00-t785.00_portrait_POST.mp4;C:\\Users\\scott\\soccer-video\\out\\portrait_reels\\branded\\008__2025-10-04__TSC_vs_FC_Tulsa_Black__BUILD_UP_SHOT__t1025.00-t1040.00_portrait_POST.mp4;C:\\Users\\scott\\soccer-video\\out\\portrait_reels\\branded\\009__2025-10-04__TSC_vs_FC_Tulsa_Black__PRESSURE_SHOT__t1046.00-t1057.00_portrait_POST.mp4;C:\\Users\\scott\\soccer-video\\out\\portrait_reels\\branded\\010__2025-10-04__TSC_vs_FC_Tulsa_Black__BUILD_UP_SHOT__t1058.00-t1080.00_portrait_POST.mp4;C:\\Users\\scott\\soccer-video\\out\\portrait_reels\\branded\\011__2025-10-04__TSC_vs_FC_Tulsa_Black__BUILD_UP_SHOT__t1198.00-t1222.00_portrait_POST.mp4;C:\\Users\\scott\\soccer-video\\out\\portrait_reels\\branded\\012__2025-10-04__TSC_vs_FC_Tulsa_Black__PRESSURE_GOAL__t1239.00-t1253.00_portrait_POST.mp4;C:\\Users\\scott\\soccer-video\\out\\portrait_reels\\branded\\013__2025-10-04__TSC_vs_FC_Tulsa_Black__BUILD_UP_PLAY__t1290.00-t1306.00_portrait_POST.mp4;C:\\Users\\scott\\soccer-video\\out\\portrait_reels\\branded\\014__2025-10-04__TSC_vs_FC_Tulsa_Black__SHOT__t1626.00-t1637.00_portrait_POST.mp4;C:\\Users\\scott\\soccer-video\\out\\portrait_reels\\branded\\015__2025-10-04__TSC_vs_FC_Tulsa_Black__BUILD_UP_SHOT__t1705.00-t1721.00_portrait_POST.mp4",
        "proxy_exists":  "true",
        "trf_exists":  "true",
        "stabilized_exists":  "true",
        "has_branded":  "true",
        "notes":  "seen in legacy index"
    },
    {
        "clip_id":  "2|2025-10-04|TSC|FC_Tulsa_Black|BUILD_UP|421.00|449",
        "index":  2,
        "date":  "2025-10-04",
        "homeTeam":  "TSC",
        "awayTeam":  "FC_Tulsa_Black",
        "label":  "BUILD_UP",
        "tStart":  421,
        "tEnd":  449,
        "duration_sec":  28,
        "orientation":  "portrait",
        "hasDebug":  false,
        "hasFinal":  true,
        "root_dir":  "C:\\Users\\scott\\soccer-video\\out\\autoframe_work\\cinematic\\002__2025-10-04__TSC_vs_FC_Tulsa_Black__BUILD_UP__t421.00-t449.00_portrait_FINAL",
        "proxy_path":  "C:\\Users\\scott\\soccer-video\\out\\autoframe_work\\cinematic\\002__2025-10-04__TSC_vs_FC_Tulsa_Black__BUILD_UP__t421.00-t449.00_portrait_FINAL\\proxy.mp4",
        "trf_path":  "C:\\Users\\scott\\soccer-video\\out\\autoframe_work\\cinematic\\002__2025-10-04__TSC_vs_FC_Tulsa_Black__BUILD_UP__t421.00-t449.00_portrait_FINAL\\follow\\transforms.trf",
        "stabilized_path":  "C:\\Users\\scott\\soccer-video\\out\\autoframe_work\\cinematic\\002__2025-10-04__TSC_vs_FC_Tulsa_Black__BUILD_UP__t421.00-t449.00_portrait_FINAL\\follow\\stabilized.mp4",
        "branded_matches":  "C:\\Users\\scott\\soccer-video\\out\\portrait_reels\\branded\\001__2025-10-04__TSC_vs_FC_Tulsa_Black__DRIBBLING__t387.00-t412.00_portrait_BRAND.mp4;C:\\Users\\scott\\soccer-video\\out\\portrait_reels\\branded\\001__2025-10-04__TSC_vs_FC_Tulsa_Black__DRIBBLING__t387.00-t412.00_portrait_POST.mp4;C:\\Users\\scott\\soccer-video\\out\\portrait_reels\\branded\\002__2025-10-04__TSC_vs_FC_Tulsa_Black__BUILD_UP__t421.00-t449.00_portrait_POST.mp4;C:\\Users\\scott\\soccer-video\\out\\portrait_reels\\branded\\003__2025-10-04__TSC_vs_FC_Tulsa_Black__BUILD_UP__t458.00-t487.00_portrait_POST.mp4;C:\\Users\\scott\\soccer-video\\out\\portrait_reels\\branded\\004__2025-10-04__TSC_vs_FC_Tulsa_Black__BUILD_UP__t495.00-t513.00_portrait_POST.mp4;C:\\Users\\scott\\soccer-video\\out\\portrait_reels\\branded\\005__2025-10-04__TSC_vs_FC_Tulsa_Black__SHOT__t600.00-t607.00_portrait_POST.mp4;C:\\Users\\scott\\soccer-video\\out\\portrait_reels\\branded\\006__2025-10-04__TSC_vs_FC_Tulsa_Black__BUILD_UP_GOAL__t674.00-t717.00_portrait_POST.mp4;C:\\Users\\scott\\soccer-video\\out\\portrait_reels\\branded\\007__2025-10-04__TSC_vs_FC_Tulsa_Black__BUILD_UP_SHOT__t767.00-t785.00_portrait_POST.mp4;C:\\Users\\scott\\soccer-video\\out\\portrait_reels\\branded\\008__2025-10-04__TSC_vs_FC_Tulsa_Black__BUILD_UP_SHOT__t1025.00-t1040.00_portrait_POST.mp4;C:\\Users\\scott\\soccer-video\\out\\portrait_reels\\branded\\009__2025-10-04__TSC_vs_FC_Tulsa_Black__PRESSURE_SHOT__t1046.00-t1057.00_portrait_POST.mp4;C:\\Users\\scott\\soccer-video\\out\\portrait_reels\\branded\\010__2025-10-04__TSC_vs_FC_Tulsa_Black__BUILD_UP_SHOT__t1058.00-t1080.00_portrait_POST.mp4;C:\\Users\\scott\\soccer-video\\out\\portrait_reels\\branded\\011__2025-10-04__TSC_vs_FC_Tulsa_Black__BUILD_UP_SHOT__t1198.00-t1222.00_portrait_POST.mp4;C:\\Users\\scott\\soccer-video\\out\\portrait_reels\\branded\\012__2025-10-04__TSC_vs_FC_Tulsa_Black__PRESSURE_GOAL__t1239.00-t1253.00_portrait_POST.mp4;C:\\Users\\scott\\soccer-video\\out\\portrait_reels\\branded\\013__2025-10-04__TSC_vs_FC_Tulsa_Black__BUILD_UP_PLAY__t1290.00-t1306.00_portrait_POST.mp4;C:\\Users\\scott\\soccer-video\\out\\portrait_reels\\branded\\014__2025-10-04__TSC_vs_FC_Tulsa_Black__SHOT__t1626.00-t1637.00_portrait_POST.mp4;C:\\Users\\scott\\soccer-video\\out\\portrait_reels\\branded\\015__2025-10-04__TSC_vs_FC_Tulsa_Black__BUILD_UP_SHOT__t1705.00-t1721.00_portrait_POST.mp4",
        "proxy_exists":  "true",
        "trf_exists":  "true",
        "stabilized_exists":  "true",
        "has_branded":  "true",
        "notes":  "seen in legacy index"
    },
    {
        "clip_id":  "15|2025-10-04|TSC|FC_Tulsa_Black|BUILD_UP_SHOT|1705.00|1721",
        "index":  15,
        "date":  "2025-10-04",
        "homeTeam":  "TSC",
        "awayTeam":  "FC_Tulsa_Black",
        "label":  "BUILD_UP_SHOT",
        "tStart":  1705,
        "tEnd":  1721,
        "duration_sec":  16,
        "orientation":  "portrait",
        "hasDebug":  false,
        "hasFinal":  true,
        "root_dir":  "C:\\Users\\scott\\soccer-video\\out\\autoframe_work\\cinematic\\015__2025-10-04__TSC_vs_FC_Tulsa_Black__BUILD_UP_SHOT__t1705.00-t1721.00_portrait_FINAL",
        "proxy_path":  "C:\\Users\\scott\\soccer-video\\out\\autoframe_work\\cinematic\\015__2025-10-04__TSC_vs_FC_Tulsa_Black__BUILD_UP_SHOT__t1705.00-t1721.00_portrait_FINAL\\proxy.mp4",
        "trf_path":  "C:\\Users\\scott\\soccer-video\\out\\autoframe_work\\cinematic\\015__2025-10-04__TSC_vs_FC_Tulsa_Black__BUILD_UP_SHOT__t1705.00-t1721.00_portrait_FINAL\\follow\\transforms.trf",
        "stabilized_path":  "C:\\Users\\scott\\soccer-video\\out\\autoframe_work\\cinematic\\015__2025-10-04__TSC_vs_FC_Tulsa_Black__BUILD_UP_SHOT__t1705.00-t1721.00_portrait_FINAL\\follow\\stabilized.mp4",
        "branded_matches":  "C:\\Users\\scott\\soccer-video\\out\\portrait_reels\\branded\\001__2025-10-04__TSC_vs_FC_Tulsa_Black__DRIBBLING__t387.00-t412.00_portrait_BRAND.mp4;C:\\Users\\scott\\soccer-video\\out\\portrait_reels\\branded\\001__2025-10-04__TSC_vs_FC_Tulsa_Black__DRIBBLING__t387.00-t412.00_portrait_POST.mp4;C:\\Users\\scott\\soccer-video\\out\\portrait_reels\\branded\\002__2025-10-04__TSC_vs_FC_Tulsa_Black__BUILD_UP__t421.00-t449.00_portrait_POST.mp4;C:\\Users\\scott\\soccer-video\\out\\portrait_reels\\branded\\003__2025-10-04__TSC_vs_FC_Tulsa_Black__BUILD_UP__t458.00-t487.00_portrait_POST.mp4;C:\\Users\\scott\\soccer-video\\out\\portrait_reels\\branded\\004__2025-10-04__TSC_vs_FC_Tulsa_Black__BUILD_UP__t495.00-t513.00_portrait_POST.mp4;C:\\Users\\scott\\soccer-video\\out\\portrait_reels\\branded\\005__2025-10-04__TSC_vs_FC_Tulsa_Black__SHOT__t600.00-t607.00_portrait_POST.mp4;C:\\Users\\scott\\soccer-video\\out\\portrait_reels\\branded\\006__2025-10-04__TSC_vs_FC_Tulsa_Black__BUILD_UP_GOAL__t674.00-t717.00_portrait_POST.mp4;C:\\Users\\scott\\soccer-video\\out\\portrait_reels\\branded\\007__2025-10-04__TSC_vs_FC_Tulsa_Black__BUILD_UP_SHOT__t767.00-t785.00_portrait_POST.mp4;C:\\Users\\scott\\soccer-video\\out\\portrait_reels\\branded\\008__2025-10-04__TSC_vs_FC_Tulsa_Black__BUILD_UP_SHOT__t1025.00-t1040.00_portrait_POST.mp4;C:\\Users\\scott\\soccer-video\\out\\portrait_reels\\branded\\009__2025-10-04__TSC_vs_FC_Tulsa_Black__PRESSURE_SHOT__t1046.00-t1057.00_portrait_POST.mp4;C:\\Users\\scott\\soccer-video\\out\\portrait_reels\\branded\\010__2025-10-04__TSC_vs_FC_Tulsa_Black__BUILD_UP_SHOT__t1058.00-t1080.00_portrait_POST.mp4;C:\\Users\\scott\\soccer-video\\out\\portrait_reels\\branded\\011__2025-10-04__TSC_vs_FC_Tulsa_Black__BUILD_UP_SHOT__t1198.00-t1222.00_portrait_POST.mp4;C:\\Users\\scott\\soccer-video\\out\\portrait_reels\\branded\\012__2025-10-04__TSC_vs_FC_Tulsa_Black__PRESSURE_GOAL__t1239.00-t1253.00_portrait_POST.mp4;C:\\Users\\scott\\soccer-video\\out\\portrait_reels\\branded\\013__2025-10-04__TSC_vs_FC_Tulsa_Black__BUILD_UP_PLAY__t1290.00-t1306.00_portrait_POST.mp4;C:\\Users\\scott\\soccer-video\\out\\portrait_reels\\branded\\014__2025-10-04__TSC_vs_FC_Tulsa_Black__SHOT__t1626.00-t1637.00_portrait_POST.mp4;C:\\Users\\scott\\soccer-video\\out\\portrait_reels\\branded\\015__2025-10-04__TSC_vs_FC_Tulsa_Black__BUILD_UP_SHOT__t1705.00-t1721.00_portrait_POST.mp4",
        "proxy_exists":  "true",
        "trf_exists":  "true",
        "stabilized_exists":  "true",
        "has_branded":  "true",
        "notes":  "seen in legacy index"
    }
]
